[
  { "Data": "01/01", "Comemorar": "Dia da Fraternidade Universal" },
  { "Data": "01/01", "Comemorar": "Dia do Mercosul" },
  { "Data": "02/01", "Comemorar": "Dia de São Macário" },
  { "Data": "03/01", "Comemorar": "Dia do Juiz de Menores" },
  { "Data": "03/01", "Comemorar": "Día del Fotógrafo Iberoamericano" },
  { "Data": "04/01", "Comemorar": "Dia Nacional da Abreugrafia" },
  { "Data": "04/01", "Comemorar": "Dia do Hemofílico" },
  { "Data": "04/01", "Comemorar": "Dia de Santa Ângela" },
  { "Data": "05/01", "Comemorar": "Dia de São Nepomuceno Neumann" },
  { "Data": "06/01", "Comemorar": "Dia da Gratidão" },
  { "Data": "06/01", "Comemorar": "Dia do Mensageiro" },
  { "Data": "06/01", "Comemorar": "Dia dos Reis Magos" },
  { "Data": "06/01", "Comemorar": "Dia dos Astrólogos" },
  { "Data": "07/01", "Comemorar": "Dia do Leitor" },
  { "Data": "07/01", "Comemorar": "Dia da Liberdade de Cultos" },
  { "Data": "08/01", "Comemorar": "Dia Nacional da Fotografia" },
  { "Data": "09/01", "Comemorar": "Dia do Astronauta" },
  { "Data": "10/01", "Comemorar": "Dia de São Gonçalo" },
  { "Data": "10/01", "Comemorar": "Peculiar People Day" },
  { "Data": "11/01", "Comemorar": "Dia de São Teodósio" },
  {
    "Data": "11/01",
    "Comemorar": "Dia do Controle da Poluição por Agrotóxicos"
  },
  { "Data": "12/01", "Comemorar": "Dia de São Fulgêncio" },
  { "Data": "12/01", "Comemorar": "Aniversário da Cidade de Belém - PA" },
  { "Data": "12/01", "Comemorar": "Dia Nacional do Empresário Contábil" },
  { "Data": "13/01", "Comemorar": "Dia de Santo Hilário de Poitiers" },
  { "Data": "14/01", "Comemorar": "Dia Mundial dos Enfermos" },
  { "Data": "14/01", "Comemorar": "Dia do Treinador de Futebol" },
  { "Data": "14/01", "Comemorar": "International Beatles Freak Day" },
  { "Data": "15/01", "Comemorar": "Dia Mundial do Compositor" },
  { "Data": "15/01", "Comemorar": "Martin Luther King Day" },
  { "Data": "16/01", "Comemorar": "Dia do Cortador de Cana-de-Açúcar" },
  { "Data": "17/01", "Comemorar": "Dia dos Tribunais de Contas do Brasil" },
  { "Data": "17/01", "Comemorar": "Dia de Santo Antão Abade" },
  { "Data": "18/01", "Comemorar": "Dia Internacional do Riso" },
  { "Data": "18/01", "Comemorar": "Dia Nacional do Krav Maga" },
  { "Data": "19/01", "Comemorar": "Dia de São Canuto" },
  {
    "Data": "19/01",
    "Comemorar": "Dia Oficial do Cabelereiro (também comemorado em 06/09)"
  },
  { "Data": "19/01", "Comemorar": "Dia do Passista" },
  { "Data": "20/01", "Comemorar": "Dia do Farmacêutico" },
  { "Data": "20/01", "Comemorar": "Dia de São Sebastião" },
  { "Data": "20/01", "Comemorar": "Dia Nacional da Parteira Tradicional" },
  { "Data": "20/01", "Comemorar": "Dia Nacional do Fusca" },
  { "Data": "20/01", "Comemorar": "Dia Mundial do Queijo" },
  { "Data": "21/01", "Comemorar": "Dia Mundial das Religiões" },
  {
    "Data": "21/01",
    "Comemorar": "Dia Nacional de Combate à Intolerância Religiosa"
  },
  { "Data": "22/01", "Comemorar": "Dia do Senado" },
  { "Data": "23/01", "Comemorar": "Dia de Santo Ildefonso" },
  { "Data": "24/01", "Comemorar": "Dia Nacional do Aposentado" },
  { "Data": "24/01", "Comemorar": "Dia Nacional da Previdência Social" },
  { "Data": "25/01", "Comemorar": "Dia do Carteiro" },
  { "Data": "25/01", "Comemorar": "Dia do Mercador" },
  { "Data": "25/01", "Comemorar": "Aniversário da Cidade de São Paulo" },
  { "Data": "25/01", "Comemorar": "Dia Nacional da Bossa Nova" },
  { "Data": "26/01", "Comemorar": "Dia de São Timóteo" },
  { "Data": "27/01", "Comemorar": "Dia do Orador" },
  {
    "Data": "27/01",
    "Comemorar": "Dia Internacional em Memória das Vítimas do Holocausto"
  },
  { "Data": "28/01", "Comemorar": "Dia do Comércio Exterior" },
  { "Data": "28/01", "Comemorar": "Dia do Portuário" },
  { "Data": "28/01", "Comemorar": "Dia de Santo Tomás de Aquino" },
  {
    "Data": "28/01",
    "Comemorar": "Dia Nacional de Combate ao Trabalho Escravo"
  },
  {
    "Data": "28/01",
    "Comemorar": "Dia Mundial de Combate à Hanseníase em 2024"
  },
  { "Data": "29/01", "Comemorar": "Dia da Hospitalidade" },
  { "Data": "29/01", "Comemorar": "Dia do Jornalista Católico" },
  { "Data": "29/01", "Comemorar": "Dia Nacional da Visibilidade Trans" },
  { "Data": "30/01", "Comemorar": "Dia da Não-Violência e da Paz" },
  { "Data": "30/01", "Comemorar": "Dia da Saudade" },
  { "Data": "30/01", "Comemorar": "Dia da Ginástica Olímpica" },
  { "Data": "30/01", "Comemorar": "Dia Nacional das Histórias em Quadrinhos" },
  { "Data": "31/01", "Comemorar": "Dia Mundial da Solidariedade" },
  { "Data": "31/01", "Comemorar": "Dia Mundial do Mágico" },
  { "Data": "31/01", "Comemorar": "Dia de São João Bosco" },
  {
    "Data": "31/01",
    "Comemorar": "Dia Nacional das Reservas Particulares do Patrimônio Natural"
  },
  { "Data": "01/02", "Comemorar": "Dia do Publicitário" },
  { "Data": "01/02", "Comemorar": "Dia do Eletricitário Gaúcho" },
  { "Data": "01/02", "Comemorar": "Dia Mundial de Mudar sua Senha" },
  { "Data": "01/02", "Comemorar": "Dia do Herói da Polícia Civil (SP)" },
  { "Data": "01/02", "Comemorar": "Dia Mundial do Hijab (World Hijab Day)" },
  { "Data": "01/02", "Comemorar": "Follow a Museum Day" },
  { "Data": "02/02", "Comemorar": "Dia do Agente Fiscal" },
  { "Data": "02/02", "Comemorar": "Dia Mundial das Zonas Úmidas" },
  { "Data": "02/02", "Comemorar": "Dia de Iemanjá" },
  { "Data": "02/02", "Comemorar": "Dia Mundial da Vida Consagrada" },
  { "Data": "03/02", "Comemorar": "Dia de São Brás" },
  { "Data": "03/02", "Comemorar": "Dia da Aviação de Asas Rotativas" },
  { "Data": "03/02", "Comemorar": "Dia do Beisebol (SP)" },
  { "Data": "04/02", "Comemorar": "Dia de São João de Brito" },
  { "Data": "04/02", "Comemorar": "Dia Mundial do Câncer" },
  { "Data": "04/02", "Comemorar": "Dia da Aliança Batista Mundial em 2024" },
  { "Data": "05/02", "Comemorar": "Dia da Papiloscopia" },
  { "Data": "05/02", "Comemorar": "Dia de Santa Ágata" },
  { "Data": "05/02", "Comemorar": "Dia do Dermatologista" },
  { "Data": "05/02", "Comemorar": "Dia Nacional da Mamografia" },
  { "Data": "05/02", "Comemorar": "Dia do Educador Penitenciário (AP)" },
  { "Data": "05/02", "Comemorar": "Dia Mundial da Nutella" },
  { "Data": "06/02", "Comemorar": "Dia do Agente de Defesa Ambiental" },
  {
    "Data": "06/02",
    "Comemorar": "Dia Internacional da Tolerância Zero à Mutilação Genital Feminina"
  },
  { "Data": "07/02", "Comemorar": "Dia Nacional do Gráfico" },
  { "Data": "08/02", "Comemorar": "Dia de São Jerônimo Emiliano" },
  { "Data": "08/02", "Comemorar": "Dia do Quadro do Magistério do Exército" },
  {
    "Data": "08/02",
    "Comemorar": "Dia Estadual do Empreendedor Individual (PE)"
  },
  { "Data": "09/02", "Comemorar": "Dia de São Miguel Febres" },
  { "Data": "10/02", "Comemorar": "Dia de Santa Escolástica" },
  { "Data": "10/02", "Comemorar": "Dia Estadual da Literatura (AP)" },
  {
    "Data": "10/02",
    "Comemorar": "Dia do Agente de Atividades Penitenciárias (DF)"
  },
  { "Data": "10/02", "Comemorar": "Dia Mundial do Feijão" },
  { "Data": "10/02", "Comemorar": "National Cream Cheese Brownie Day" },
  { "Data": "11/02", "Comemorar": "Dia de Nossa Senhora de Lourdes" },
  { "Data": "11/02", "Comemorar": "Dia do Campeiro (RS)" },
  { "Data": "11/02", "Comemorar": "Dia do Caminho da Fé (SP)" },
  { "Data": "11/02", "Comemorar": "Dia do Zelador" },
  { "Data": "11/02", "Comemorar": "Dia Mundial do Doente" },
  { "Data": "11/02", "Comemorar": "Domingo de Carnaval em 2024" },
  { "Data": "12/02", "Comemorar": "Dia de Santa Eulália" },
  {
    "Data": "12/02",
    "Comemorar": "Dia do Empregado em Edifícios de São Paulo"
  },
  { "Data": "12/02", "Comemorar": "Dia Mundial do Matrimônio" },
  {
    "Data": "12/02",
    "Comemorar": "Dia Internacional contra o Uso de Crianças-Soldado"
  },
  { "Data": "12/02", "Comemorar": "European Epilepsy Day em 2024" },
  {
    "Data": "13/02",
    "Comemorar": "Dia do Serviço de Assistência Religiosa do Exército"
  },
  { "Data": "13/02", "Comemorar": "Dia dos Solteiros" },
  { "Data": "13/02", "Comemorar": "Dia do Procurador do Estado da Paraíba" },
  { "Data": "13/02", "Comemorar": "World Radio Day" },
  { "Data": "13/02", "Comemorar": "Carnaval em 2024" },
  { "Data": "14/02", "Comemorar": "Dia de São Valentim" },
  { "Data": "14/02", "Comemorar": "Dia de São Cirilo" },
  { "Data": "14/02", "Comemorar": "Dia do Botonista (SP)" },
  {
    "Data": "14/02",
    "Comemorar": "Quarta-feira de cinzas (início da quaresma) em 2024"
  },
  { "Data": "15/02", "Comemorar": "Dia de São Cláudio de La Colombiére" },
  {
    "Data": "15/02",
    "Comemorar": "Dia Internacional do Combate ao Câncer Infantil"
  },
  { "Data": "16/02", "Comemorar": "Dia Nacional do Repórter" },
  {
    "Data": "16/02",
    "Comemorar": "Dia Estadual de Luta Contra a Poluição Atmosférica (ES)"
  },
  {
    "Data": "17/02",
    "Comemorar": "Dia dos Sete Fundadores da Ordem dos Servitas"
  },
  {
    "Data": "17/02",
    "Comemorar": "Dia Estadual da Renovação Carismática Católica (GO)"
  },
  {
    "Data": "17/02",
    "Comemorar": "Dia Mundial da Espiritualidade Humana (World Human Spirit Day)"
  },
  { "Data": "17/02", "Comemorar": "Día del Grito de Libertad Andaluz" },
  { "Data": "17/02", "Comemorar": "Dia do Gato (também comemorado em 08/08)" },
  { "Data": "18/02", "Comemorar": "Dia de Santa Bernardete Soubirous" },
  {
    "Data": "18/02",
    "Comemorar": "Dia Estadual do Surfe e dos Surfistas (SC)"
  },
  { "Data": "18/02", "Comemorar": "Dia do Líder Comunitário (AC)" },
  { "Data": "18/02", "Comemorar": "Dia Catarinense da Yôga" },
  { "Data": "18/02", "Comemorar": "Dia do Ensino Médio no Brasil" },
  { "Data": "18/02", "Comemorar": "Dia Internacional da Síndrome de Asperger" },
  { "Data": "18/02", "Comemorar": "Día de la Mujer de las Américas" },
  { "Data": "19/02", "Comemorar": "Dia do Esporte" },
  { "Data": "20/02", "Comemorar": "Dia de Santo Eleutério" },
  { "Data": "20/02", "Comemorar": "International Pipe Smoking Day" },
  { "Data": "21/02", "Comemorar": "Dia da Tomada de Monte Castelo pela FEB" },
  { "Data": "21/02", "Comemorar": "Dia Nacional do Naturismo" },
  { "Data": "21/02", "Comemorar": "Dia Internacional da Língua Materna" },
  { "Data": "21/02", "Comemorar": "Dia Nacional do Imigrante Italiano" },
  { "Data": "21/02", "Comemorar": "Dia de São Pedro Damião" },
  { "Data": "22/02", "Comemorar": "Dia de Cátedra de São Pedro Apóstolo." },
  { "Data": "22/02", "Comemorar": "Dia dos Arautos do Evangelho (SP)" },
  { "Data": "22/02", "Comemorar": "Dia Internacional do Maçom" },
  { "Data": "22/02", "Comemorar": "European Day for Victims of Crime" },
  { "Data": "23/02", "Comemorar": "Dia Nacional do Rotariano" },
  { "Data": "23/02", "Comemorar": "Dia do Surdo-Mudo" },
  { "Data": "24/02", "Comemorar": "Dia de São Sérgio" },
  {
    "Data": "24/02",
    "Comemorar": "Dia da Conquista do Voto Feminino no Brasil"
  },
  { "Data": "24/02", "Comemorar": "Dia Municipal da Defesa Civil - SP" },
  { "Data": "25/02", "Comemorar": "Dia de São Tarásio" },
  { "Data": "26/02", "Comemorar": "Dia de Santo Alexandre" },
  { "Data": "26/02", "Comemorar": "Dia do Comediante" },
  { "Data": "27/02", "Comemorar": "Dia Nacional do Livro Didático" },
  { "Data": "27/02", "Comemorar": "Dia do Agente Fiscal da Receita Federal" },
  { "Data": "28/02", "Comemorar": "Dia de São Leandro" },
  {
    "Data": "28/02",
    "Comemorar": "Dia Internacional de Combate e Prevenção às LER/DORT"
  },
  { "Data": "28/02", "Comemorar": "Dia Estadual da Cultura de Bois (PE)" },
  { "Data": "28/02", "Comemorar": "Dia da Ressaca" },
  { "Data": "28/02", "Comemorar": "Día de Andalucía" },
  { "Data": "29/02", "Comemorar": "Dia de Santo Osvaldo" },
  { "Data": "01/03", "Comemorar": "Aniversário da cidade do Rio de Janeiro" },
  { "Data": "01/03", "Comemorar": "Dia da Criança Doente" },
  { "Data": "01/03", "Comemorar": "Dia do Turismo Ecológico" },
  { "Data": "01/03", "Comemorar": "Dia de ser carioca" },
  { "Data": "02/03", "Comemorar": "Dia Nacional do Turismo" },
  { "Data": "02/03", "Comemorar": "Dia da Vindima (Colheita de Uvas)" },
  { "Data": "02/03", "Comemorar": "Dia de Santa Maria (DF)" },
  { "Data": "02/03", "Comemorar": "International Rescue Cat Day" },
  { "Data": "03/03", "Comemorar": "Dia Nacional do Meteorologista" },
  { "Data": "03/03", "Comemorar": "Dia do Seringueiro" },
  { "Data": "03/03", "Comemorar": "Dia dos Intendentes da Marinha" },
  {
    "Data": "03/03",
    "Comemorar": "Dia dos Dirigentes das Soc. Desportivas, Culturais e Assistenciais"
  },
  { "Data": "03/03", "Comemorar": "Dia Mundial da Vida Silvestre" },
  { "Data": "03/03", "Comemorar": "Dia da Esposa do Pastor em 2024" },
  { "Data": "04/03", "Comemorar": "Dia de São Casimiro" },
  {
    "Data": "04/03",
    "Comemorar": "Dia Mundial da Obesidade e Dia Nacional de Prevenção da Obesidade"
  },
  { "Data": "05/03", "Comemorar": "Dia do Filatelista Brasileiro" },
  { "Data": "05/03", "Comemorar": "Dia da Integração Cooperativista" },
  { "Data": "05/03", "Comemorar": "Dia de São Teófilo" },
  { "Data": "06/03", "Comemorar": "Dia de Santa Rosa de Viterbo" },
  { "Data": "06/03", "Comemorar": "Dia Mundial da Oreo" },
  { "Data": "07/03", "Comemorar": "Dia Mundial da Prece" },
  { "Data": "07/03", "Comemorar": "Dia do Fuzileiro Naval" },
  { "Data": "08/03", "Comemorar": "Dia Internacional da Mulher" },
  { "Data": "08/03", "Comemorar": "Dia de São Patrício" },
  { "Data": "09/03", "Comemorar": "Dia de Santa Francisca Romana" },
  { "Data": "09/03", "Comemorar": "Dia Internacional do DJ - World DJ Day" },
  { "Data": "09/03", "Comemorar": "Dia de Combate à Dengue (CE) em 2024" },
  { "Data": "10/03", "Comemorar": "Dia do Sogro" },
  { "Data": "10/03", "Comemorar": "Dia do Telefone" },
  {
    "Data": "10/03",
    "Comemorar": "Dia Estadual do Assistente de Educação (SC)"
  },
  {
    "Data": "10/03",
    "Comemorar": "Dia da Mobilização Contra o Aquecimento Global (CE)"
  },
  { "Data": "10/03", "Comemorar": "Dia do Missionário Evangélico (PE)" },
  { "Data": "10/03", "Comemorar": "Dia das Associações de Moradores (RJ)" },
  { "Data": "10/03", "Comemorar": "Middle Name Pride Day" },
  { "Data": "10/03", "Comemorar": "National Mario Day" },
  { "Data": "10/03", "Comemorar": "Dia Mundial de Combate ao Sedentarismo " },
  { "Data": "11/03", "Comemorar": "Dia de Santa Flora" },
  { "Data": "11/03", "Comemorar": "Dia do Motociclista (SP)" },
  { "Data": "11/03", "Comemorar": "Johnny Appleseed Day" },
  { "Data": "12/03", "Comemorar": "Dia do Bibliotecário" },
  { "Data": "12/03", "Comemorar": "National Alfred Hitchcock Day" },
  { "Data": "13/03", "Comemorar": "Dia Estadual da Caridade Irmã Dulce - BA" },
  { "Data": "13/03", "Comemorar": "Dia do Conservacionismo" },
  { "Data": "13/03", "Comemorar": "Dia da Prevenção à Doença Renal (PR)" },
  { "Data": "13/03", "Comemorar": "Dia Mundial do Rotaract" },
  { "Data": "14/03", "Comemorar": "Dia Mundial da Poesia" },
  { "Data": "14/03", "Comemorar": "Dia Mundial da Incontinência Urinária" },
  { "Data": "14/03", "Comemorar": "Dia do Vendedor de Livros" },
  { "Data": "14/03", "Comemorar": "Dia dos Carecas" },
  { "Data": "14/03", "Comemorar": "Dia do Pi" },
  { "Data": "14/03", "Comemorar": "Dia mundial do rim em 2024" },
  { "Data": "15/03", "Comemorar": "Dia Internacional da Defesa do Consumidor" },
  { "Data": "15/03", "Comemorar": "Dia Estadual de Combate ao Fumo (PB)" },
  { "Data": "15/03", "Comemorar": "Dia do Voluntário (RJ)" },
  {
    "Data": "15/03",
    "Comemorar": "International Day of Protest against the Canadian Seal Hunt"
  },
  { "Data": "15/03", "Comemorar": "Dia Mundial do Sono em 2024" },
  { "Data": "16/03", "Comemorar": "Dia de Santa Luísa de Marillac" },
  { "Data": "16/03", "Comemorar": "Dia Nacional do Ouvidor" },
  { "Data": "16/03", "Comemorar": "Dia do Agente Penitenciário Federal" },
  { "Data": "16/03", "Comemorar": "Dia da Bandeira do Estado do Paraná" },
  { "Data": "17/03", "Comemorar": "Dia de São Patrício" },
  {
    "Data": "17/03",
    "Comemorar": "Dia Estadual da Bacia Hidrográfica do Rio dos Sinos (RS)"
  },
  { "Data": "18/03", "Comemorar": "Dia de São Cirilo de Jerusalém" },
  { "Data": "18/03", "Comemorar": "Dia do DeMolay" },
  { "Data": "18/03", "Comemorar": "Dia da Imigração Judaica" },
  { "Data": "19/03", "Comemorar": "Dia da Escola" },
  { "Data": "19/03", "Comemorar": "Dia dos Moribundos" },
  { "Data": "19/03", "Comemorar": "Dia Mundial do Artesão" },
  { "Data": "19/03", "Comemorar": "Dia do Carpinteiro" },
  { "Data": "19/03", "Comemorar": "Dia de São José" },
  { "Data": "20/03", "Comemorar": "Dia de Santo Ambrósio de Sena" },
  { "Data": "20/03", "Comemorar": "Dia Mundial da Felicidade" },
  { "Data": "20/03", "Comemorar": "Dia Mundial Sem Carne (Meat Out Day)" },
  {
    "Data": "20/03",
    "Comemorar": "Dia Internacional do Contador de Histórias"
  },
  { "Data": "20/03", "Comemorar": "Dia Nacional de Atenção à Disfagia" },
  { "Data": "21/03", "Comemorar": "Dia Mundial da Infância" },
  { "Data": "21/03", "Comemorar": "Dia Internacional da Síndrome de Down" },
  {
    "Data": "21/03",
    "Comemorar": "Día Internacional da Eliminação da Discriminação Racial"
  },
  { "Data": "21/03", "Comemorar": "Dia da Memória e do Compromisso (Itália)" },
  { "Data": "21/03", "Comemorar": "Início do outono no hemisfério sul" },
  { "Data": "21/03", "Comemorar": "Início da primavera no hemisfério norte" },
  { "Data": "22/03", "Comemorar": "Dia Mundial da Água" },
  { "Data": "22/03", "Comemorar": "Dia do Rio Sorocaba" },
  {
    "Data": "22/03",
    "Comemorar": "Dia Estadual de Defesa do Rio Paraíba do Sul (RJ)"
  },
  { "Data": "23/03", "Comemorar": "Dia Mundial do Meteorologista" },
  { "Data": "23/03", "Comemorar": "Aniversário da Cidade de Florianópolis" },
  { "Data": "23/03", "Comemorar": "Dia do Naturólogo (SC)" },
  { "Data": "23/03", "Comemorar": "Dia do Agronegócio (MT)" },
  { "Data": "24/03", "Comemorar": "Dia Mundial de Combate à Tuberculose" },
  { "Data": "24/03", "Comemorar": "Dia Internacional do Direito à Verdade" },
  { "Data": "24/03", "Comemorar": "Domingo de Ramos em 2024" },
  { "Data": "25/03", "Comemorar": "Dia do Especialista em Aeronáutica" },
  { "Data": "25/03", "Comemorar": "Dia da Anunciação do Senhor" },
  { "Data": "25/03", "Comemorar": "Data Magna do Ceará" },
  { "Data": "25/03", "Comemorar": "Dia do Oficial de Justiça" },
  { "Data": "26/03", "Comemorar": "Dia do Cacau" },
  {
    "Data": "26/03",
    "Comemorar": "Dia Mundial da Conscientização da Epilepsia - Purple Day"
  },
  { "Data": "27/03", "Comemorar": "Dia do Ator" },
  { "Data": "27/03", "Comemorar": "Dia do Cinema Gaúcho" },
  { "Data": "27/03", "Comemorar": "Dia da Casa Editora Presbiteriana" },
  { "Data": "27/03", "Comemorar": "Dia Estadual da Cultura Cristã (PE)" },
  { "Data": "27/03", "Comemorar": "Dia da Inclusão Digital e Social" },
  { "Data": "27/03", "Comemorar": "Dia Mundial do Circo" },
  { "Data": "28/03", "Comemorar": "Dia do Diagramador" },
  { "Data": "28/03", "Comemorar": "Dia do Revisor" },
  { "Data": "28/03", "Comemorar": "Dia das Comunicações Navais" },
  { "Data": "29/03", "Comemorar": "Dia de São Constantino" },
  {
    "Data": "29/03",
    "Comemorar": "Dia Estadual das Micro e Pequenas Empresas (SC)"
  },
  { "Data": "29/03", "Comemorar": "Sexta-feira da Paixão em 2024" },
  { "Data": "30/03", "Comemorar": "Dia da Anestesia Geral" },
  { "Data": "30/03", "Comemorar": "Dia Mundial do Transtorno Bipolar" },
  { "Data": "30/03", "Comemorar": "Dia do Futebol Society" },
  { "Data": "30/03", "Comemorar": "Dia do Marco da Paz (SP)" },
  { "Data": "30/03", "Comemorar": "Dia da Terra Palestina" },
  { "Data": "30/03", "Comemorar": "Hora do Planeta em 2024" },
  { "Data": "30/03", "Comemorar": "Sábado de Aleluia em 2024" },
  { "Data": "31/03", "Comemorar": "Dia da Integração Nacional" },
  { "Data": "31/03", "Comemorar": "Dia do Espiritualismo Moderno" },
  { "Data": "31/03", "Comemorar": "Dia da Saúde e Nutrição" },
  { "Data": "31/03", "Comemorar": "Páscoa em 2024" },
  { "Data": "01/04", "Comemorar": "Dia da Mentira" },
  { "Data": "01/04", "Comemorar": "Dia do Tomate" },
  { "Data": "02/04", "Comemorar": "Dia Mundial do Livro Infanto-Juvenil" },
  {
    "Data": "02/04",
    "Comemorar": "Dia Mundial da Consciencialização do Autismo"
  },
  { "Data": "02/04", "Comemorar": "Dia de São Francisco de Paula" },
  {
    "Data": "02/04",
    "Comemorar": "Día del Veterano y de los Caídos en la Guerra de Malvinas"
  },
  { "Data": "03/04", "Comemorar": "Dia de São Ricardo" },
  { "Data": "03/04", "Comemorar": "Dia da Verdade" },
  { "Data": "03/04", "Comemorar": "Dia do Atuário" },
  { "Data": "03/04", "Comemorar": "Dia do Desporto Comunitário" },
  { "Data": "04/04", "Comemorar": "Dia Nacional do Parkinsoniano" },
  { "Data": "04/04", "Comemorar": "Dia do Colorado (RS)" },
  { "Data": "04/04", "Comemorar": "Dia de São Pedro de Poitiers" },
  { "Data": "05/04", "Comemorar": "Dia de São Vicente Ferrer" },
  {
    "Data": "05/04",
    "Comemorar": "Dia de Luta Contra a Criminalização dos Movimentos Sociais (SP)"
  },
  { "Data": "05/04", "Comemorar": "Palestinian Children Day" },
  { "Data": "06/04", "Comemorar": "Dia da Bem-Aventurada Pierina Morosini" },
  {
    "Data": "06/04",
    "Comemorar": "Dia de Mobilização pela Promoção da Saúde e Qualidade de Vida"
  },
  { "Data": "07/04", "Comemorar": "Dia do Corretor" },
  { "Data": "07/04", "Comemorar": "Dia do Médico Legista" },
  { "Data": "07/04", "Comemorar": "Dia Mundial da Saúde" },
  { "Data": "07/04", "Comemorar": "Dia Nacional do Jornalista" },
  { "Data": "08/04", "Comemorar": "Dia Mundial de Combate ao Câncer" },
  { "Data": "08/04", "Comemorar": "Dia da Natação" },
  { "Data": "08/04", "Comemorar": "Dia Nacional do Sistema Braille" },
  { "Data": "09/04", "Comemorar": "Dia Nacional do Aço" },
  { "Data": "09/04", "Comemorar": "Dia da Biblioteca" },
  { "Data": "10/04", "Comemorar": "Dia da Engenharia" },
  { "Data": "11/04", "Comemorar": "Dia da Escola de Samba" },
  { "Data": "11/04", "Comemorar": "Dia Mundial da Doença de Parkinson" },
  { "Data": "12/04", "Comemorar": "Dia do Médico Obstetra" },
  { "Data": "12/04", "Comemorar": "Dia Nacional do Humorista" },
  { "Data": "12/04", "Comemorar": "Dia do Corpo de Engenheiros da Marinha" },
  { "Data": "13/04", "Comemorar": "Aniversário da cidade de Fortaleza - CE" },
  { "Data": "13/04", "Comemorar": "Dia do Jovem" },
  { "Data": "13/04", "Comemorar": "Dia do Beijo" },
  { "Data": "13/04", "Comemorar": "Dia do Office Boy" },
  { "Data": "14/04", "Comemorar": "Dia das Américas" },
  { "Data": "14/04", "Comemorar": "Dia Mundial do Café" },
  { "Data": "14/04", "Comemorar": "Dia do Cafeicultor (ES)" },
  { "Data": "14/04", "Comemorar": "Dia Nacional do Médico Neurocirurgião" },
  { "Data": "15/04", "Comemorar": "Dia Mundial do Desenhista" },
  { "Data": "15/04", "Comemorar": "Dia Mundial da Conservação do Solo" },
  { "Data": "15/04", "Comemorar": "Dia do Desarmamento Infantil" },
  { "Data": "16/04", "Comemorar": "Dia Nacional do Lions Clube" },
  { "Data": "16/04", "Comemorar": "Dia Nacional da Voz" },
  { "Data": "17/04", "Comemorar": "Dia de Santo Aniceto" },
  { "Data": "17/04", "Comemorar": "Dia Nacional da Botânica" },
  { "Data": "17/04", "Comemorar": "Dia Internacional das Lutas Camponesas" },
  { "Data": "17/04", "Comemorar": "Dia Nacional de Luta pela Reforma Agrária" },
  { "Data": "17/04", "Comemorar": "Dia do Orador (CE)" },
  { "Data": "17/04", "Comemorar": "Dia do Judô (SP)" },
  { "Data": "17/04", "Comemorar": "Dia Mundial do Hemofílico" },
  { "Data": "17/04", "Comemorar": "Malbec World Day" },
  { "Data": "18/04", "Comemorar": "Dia Nacional do Livro Infantil" },
  { "Data": "18/04", "Comemorar": "Dia Internacional dos Monumentos e Sítios" },
  { "Data": "18/04", "Comemorar": "Dia dos Espíritas" },
  { "Data": "18/04", "Comemorar": "Dia Mundial do Radioamador" },
  { "Data": "19/04", "Comemorar": "Dia Nacional do Índio" },
  { "Data": "19/04", "Comemorar": "Dia do Exército Brasileiro" },
  { "Data": "19/04", "Comemorar": "Dia de Santo Expedito" },
  { "Data": "19/04", "Comemorar": "Dia Mundial da Bicicleta" },
  { "Data": "20/04", "Comemorar": "Dia do Diplomata" },
  { "Data": "20/04", "Comemorar": "Dia do Disco" },
  { "Data": "21/04", "Comemorar": "Dia do Metalúrgico" },
  { "Data": "21/04", "Comemorar": "Tiradentes" },
  { "Data": "21/04", "Comemorar": "Dia da Latinidade" },
  { "Data": "21/04", "Comemorar": "Dia da Polícia Civil" },
  { "Data": "21/04", "Comemorar": "World Creativity and Innovation Day" },
  { "Data": "22/04", "Comemorar": "Dia Nacional do Agente de Viagem" },
  { "Data": "22/04", "Comemorar": "Dia da Aviação de Caça" },
  { "Data": "22/04", "Comemorar": "Dia da Comunidade Luso-Brasileira" },
  { "Data": "22/04", "Comemorar": "Dia do Planeta Terra" },
  { "Data": "22/04", "Comemorar": "Descobrimento do Brasil" },
  { "Data": "22/04", "Comemorar": "Dia da Tontura" },
  { "Data": "23/04", "Comemorar": "Dia Mundial do Escoteiro" },
  { "Data": "23/04", "Comemorar": "Dia de São Jorge" },
  { "Data": "23/04", "Comemorar": "Dia Internacional do Livro" },
  { "Data": "23/04", "Comemorar": "Dia Nacional do Choro" },
  { "Data": "24/04", "Comemorar": "Dia do Penitenciário" },
  { "Data": "24/04", "Comemorar": "Dia Internacional do Jovem Trabalhador" },
  { "Data": "24/04", "Comemorar": "Dia Mundial de Combate à Meningite" },
  { "Data": "24/04", "Comemorar": "Dia do Churrasco" },
  {
    "Data": "24/04",
    "Comemorar": "Dia Nacional da Língua Brasileira de Sinais (Libras)"
  },
  { "Data": "25/04", "Comemorar": "Dia da Contabilidade" },
  { "Data": "25/04", "Comemorar": "Dia Nacional do Despachante Aduaneiro" },
  { "Data": "25/04", "Comemorar": "Dia da Araucária (SP)" },
  { "Data": "25/04", "Comemorar": "Dia Mundial da Malária" },
  { "Data": "25/04", "Comemorar": "Dia da Liberdade em Portugal" },
  { "Data": "25/04", "Comemorar": "Dia do DNA" },
  { "Data": "26/04", "Comemorar": "Dia do Engraxate" },
  { "Data": "26/04", "Comemorar": "Dia do Goleiro" },
  { "Data": "26/04", "Comemorar": "Dia do Juiz da Justiça do Trabalho" },
  {
    "Data": "26/04",
    "Comemorar": "Dia Nacional de Prevenção e Combate a Hipertensão"
  },
  { "Data": "27/04", "Comemorar": "Dia da Empregada Doméstica" },
  { "Data": "27/04", "Comemorar": "Dia de Santa Zita" },
  { "Data": "27/04", "Comemorar": "Dia Internacional da Anta" },
  {
    "Data": "27/04",
    "Comemorar": "Dia Mundial do Design Gráfico - World Graphics Day"
  },
  { "Data": "27/04", "Comemorar": "Dia da Liberdade na África do Sul" },
  {
    "Data": "27/04",
    "Comemorar": "Dia Mundial da Medicina Veterinária em 2024"
  },
  { "Data": "28/04", "Comemorar": "Dia da Educação" },
  { "Data": "28/04", "Comemorar": "Dia da Sogra" },
  {
    "Data": "28/04",
    "Comemorar": "Dia Mundial da Segurança e Saúde no Trabalho"
  },
  { "Data": "28/04", "Comemorar": "Dia Nacional da Caatinga" },
  {
    "Data": "28/04",
    "Comemorar": "Dia de Combate ao Acidente de Trabalho (AP)"
  },
  { "Data": "28/04", "Comemorar": "Dia da Escola Dominical em 2024" },
  { "Data": "29/04", "Comemorar": "Dia de Santa Catarina de Sena" },
  { "Data": "29/04", "Comemorar": "Dia Mundial da Dança" },
  { "Data": "29/04", "Comemorar": "Dia do Crítico Teatral" },
  { "Data": "30/04", "Comemorar": "Dia Nacional da Mulher" },
  { "Data": "30/04", "Comemorar": "Dia Nacional do Ferroviário" },
  { "Data": "30/04", "Comemorar": "Dia de São Pio V" },
  { "Data": "30/04", "Comemorar": "Dia Internacional do Jazz" },
  { "Data": "30/04", "Comemorar": "Dia da Vocação Concepcionista" },
  { "Data": "01/05", "Comemorar": "Dia do Trabalho" },
  { "Data": "01/05", "Comemorar": "Dia Mundial do Combate ao Câncer de Pele" },
  { "Data": "01/05", "Comemorar": "Dia da Literatura Brasileira" },
  { "Data": "01/05", "Comemorar": "Dia de São José Operário" },
  { "Data": "02/05", "Comemorar": "Dia de Santo Atanásio" },
  { "Data": "02/05", "Comemorar": "Dia Estadual da Saúde Mental - PR" },
  { "Data": "03/05", "Comemorar": "Dia Mundial da Liberdade de Imprensa" },
  { "Data": "03/05", "Comemorar": "Dia do Legislador" },
  { "Data": "03/05", "Comemorar": "Dia do Sertanejo" },
  { "Data": "03/05", "Comemorar": "Dia Nacional do Pau-Brasil" },
  { "Data": "03/05", "Comemorar": "Dia Estadual de Combate à Violência (PE)" },
  { "Data": "03/05", "Comemorar": "Dia Estadual da Imigração Polonesa (SC)" },
  { "Data": "03/05", "Comemorar": "Dia Mundial do Sol" },
  { "Data": "04/05", "Comemorar": "Dia de São Floriano" },
  { "Data": "04/05", "Comemorar": "Dia de Star Wars - Star Wars Day" },
  {
    "Data": "04/05",
    "Comemorar": "Dia Internacional do Combatente de Incêndios Florestais"
  },
  { "Data": "05/05", "Comemorar": "Dia do Pintor" },
  { "Data": "05/05", "Comemorar": "Dia da Arma de Comunicações (Exército)" },
  { "Data": "05/05", "Comemorar": "Dia Nacional das Comunicações" },
  { "Data": "05/05", "Comemorar": "Dia Internacional da Parteira" },
  { "Data": "05/05", "Comemorar": "Dia Mundial da Higienização das Mãos" },
  { "Data": "05/05", "Comemorar": "Dia da Língua Portuguesa" },
  { "Data": "05/05", "Comemorar": "Dia Batista de Ação Social em 2024" },
  { "Data": "06/05", "Comemorar": "Dia do Cartógrafo" },
  { "Data": "06/05", "Comemorar": "Dia do Instrumentador Cirúrgico" },
  { "Data": "06/05", "Comemorar": "Dia Nacional da Matemática" },
  { "Data": "07/05", "Comemorar": "Dia do Médico Oftalmologista" },
  { "Data": "07/05", "Comemorar": "Dia Nacional de Prevenção da Alergia" },
  { "Data": "07/05", "Comemorar": "Dia mundial de combate à asma em 2024" },
  { "Data": "08/05", "Comemorar": "Dia do Artista Plástico" },
  { "Data": "08/05", "Comemorar": "Dia do Profissional de Marketing" },
  {
    "Data": "08/05",
    "Comemorar": "Dia Nacional de Luta contra a Endometriose"
  },
  { "Data": "08/05", "Comemorar": "Dia Nacional das Hemoglobinopatias" },
  { "Data": "08/05", "Comemorar": "Día del Son Cubano" },
  { "Data": "09/05", "Comemorar": "Dia da Europa" },
  { "Data": "09/05", "Comemorar": "Dia Nacional do Empregado Sindical" },
  { "Data": "10/05", "Comemorar": "Dia do Campo" },
  { "Data": "10/05", "Comemorar": "Dia da Cavalaria" },
  { "Data": "10/05", "Comemorar": "Dia Mundial do Lúpus" },
  { "Data": "10/05", "Comemorar": "Dia da Cozinheira" },
  { "Data": "11/05", "Comemorar": "Dia de Santa Maria Bertilla Boscardin" },
  { "Data": "11/05", "Comemorar": "Dia Nacional do Frei SantAnna Galvão" },
  { "Data": "11/05", "Comemorar": "Dia Nacional do Reggae" },
  { "Data": "11/05", "Comemorar": "Dia Estadual da Construção Civil (SC)" },
  { "Data": "11/05", "Comemorar": "Dia do Empreendedorismo (DF)" },
  { "Data": "12/05", "Comemorar": "Dia Internacional da Enfermagem" },
  { "Data": "12/05", "Comemorar": "Dia Mundial da Fibromialgia" },
  { "Data": "12/05", "Comemorar": "Dia das mães em 2024" },
  {
    "Data": "12/05",
    "Comemorar": "Dia do Aniversário do Buda Shakyamuni em 2024"
  },
  { "Data": "13/05", "Comemorar": "Dia de Nossa Senhora de Fátima" },
  { "Data": "13/05", "Comemorar": "Dia do Automóvel" },
  { "Data": "13/05", "Comemorar": "Dia da Estrada de Rodagem" },
  { "Data": "13/05", "Comemorar": "Dia da Fraternidade Brasileira" },
  { "Data": "13/05", "Comemorar": "Dia do Preto Velho" },
  { "Data": "13/05", "Comemorar": "Dia do Bairro do Méier - Rio de Janeiro" },
  { "Data": "14/05", "Comemorar": "Dia do PX" },
  { "Data": "14/05", "Comemorar": "Dia do Segurado" },
  { "Data": "14/05", "Comemorar": "Dia de São Matias" },
  { "Data": "14/05", "Comemorar": "Dia da Habitação (PR)" },
  { "Data": "15/05", "Comemorar": "Dia da Assistência Social" },
  { "Data": "15/05", "Comemorar": "Dia do Gerente de Banco" },
  {
    "Data": "15/05",
    "Comemorar": "Dia Internacional do Serviço de Informações Aeronáuticas"
  },
  { "Data": "15/05", "Comemorar": "Dia de Santo Isidoro" },
  { "Data": "15/05", "Comemorar": "Dia Internacional da Latinidade" },
  { "Data": "15/05", "Comemorar": "Dia Internacional da Família" },
  { "Data": "15/05", "Comemorar": "Dia do Armamentista" },
  { "Data": "16/05", "Comemorar": "Dia do Gari" },
  { "Data": "16/05", "Comemorar": "Dia Estadual da Imigração Suíça (RJ)" },
  { "Data": "17/05", "Comemorar": "Dia Mundial das Comunicações" },
  { "Data": "17/05", "Comemorar": "Dia do Trabalhador Rural Volante" },
  { "Data": "17/05", "Comemorar": "Dia da Tecnologia da Informação (RJ)" },
  { "Data": "17/05", "Comemorar": "Dia Mundial da Internet" },
  { "Data": "17/05", "Comemorar": "Dia Internacional contra a Homofobia" },
  { "Data": "17/05", "Comemorar": "Dia Mundial da Reciclagem" },
  { "Data": "18/05", "Comemorar": "Dia da Boa Vontade" },
  { "Data": "18/05", "Comemorar": "Dia Internacional dos Museus" },
  { "Data": "18/05", "Comemorar": "Dia Nacional da Luta Antimanicomial" },
  {
    "Data": "18/05",
    "Comemorar": "Dia de Combate à Exploração Sexual Contra Crianças e Adolescentes"
  },
  { "Data": "18/05", "Comemorar": "Dia do Vidreiro" },
  { "Data": "19/05", "Comemorar": "Dia de Santo Ivo" },
  { "Data": "19/05", "Comemorar": "Dia dos Acadêmicos do Direito" },
  {
    "Data": "19/05",
    "Comemorar": "Dia da Conscientização para Doação de Leite Humano (SP)"
  },
  { "Data": "19/05", "Comemorar": "Dia Mundial de Doação de Leite Humano" },
  { "Data": "19/05", "Comemorar": "Dia Nacional da Defensoria Pública" },
  { "Data": "19/05", "Comemorar": "Dia do Físico" },
  { "Data": "19/05", "Comemorar": "Pentecostes em 2024" },
  { "Data": "20/05", "Comemorar": "Dia de São Bernardino de Sena" },
  { "Data": "20/05", "Comemorar": "Dia do Comissário de Menores" },
  { "Data": "20/05", "Comemorar": "Dia do Otimismo" },
  {
    "Data": "20/05",
    "Comemorar": "Dia Nacional do Auxiliar e Técnico de Enfermagem"
  },
  { "Data": "21/05", "Comemorar": "Dia da Língua Nacional" },
  { "Data": "21/05", "Comemorar": "Dia Estadual da Cachaça (MG)" },
  {
    "Data": "21/05",
    "Comemorar": "Dia Mundial para o Desenvolvimento Cultural"
  },
  { "Data": "22/05", "Comemorar": "Dia do Apicultor" },
  { "Data": "22/05", "Comemorar": "Dia Internacional da Biodiversidade" },
  { "Data": "22/05", "Comemorar": "Dia de Santa Rita de Cássia" },
  { "Data": "22/05", "Comemorar": "Dia do Abraço" },
  { "Data": "23/05", "Comemorar": "Dia Mundial da Comunicação Social" },
  { "Data": "24/05", "Comemorar": "Dia do Vestibulando" },
  { "Data": "24/05", "Comemorar": "Dia Nacional do Milho" },
  { "Data": "24/05", "Comemorar": "Dia do Datilógrafo" },
  { "Data": "24/05", "Comemorar": "Dia Nacional do Café" },
  { "Data": "24/05", "Comemorar": "Dia do Cafeicultor" },
  { "Data": "24/05", "Comemorar": "Dia da Arma de Infantaria" },
  { "Data": "25/05", "Comemorar": "Dia da Indústria" },
  { "Data": "25/05", "Comemorar": "Dia internacional da Criança Desaparecida" },
  { "Data": "25/05", "Comemorar": "Dia da Costureira" },
  { "Data": "25/05", "Comemorar": "Dia do Trabalhador Rural" },
  { "Data": "25/05", "Comemorar": "Dia do Trabalhador Industrial" },
  { "Data": "25/05", "Comemorar": "Dia do Orgulho Nerd" },
  {
    "Data": "25/05",
    "Comemorar": "Dia da Toalha (homenagem ao escritor Douglas Adams)"
  },
  { "Data": "25/05", "Comemorar": "Dia da Liberdade de Impostos" },
  { "Data": "25/05", "Comemorar": "Dia Internacional da Tireoide" },
  { "Data": "25/05", "Comemorar": "Dia Internacional do Sapateado" },
  { "Data": "25/05", "Comemorar": "Dia Nacional de Adoção" },
  { "Data": "26/05", "Comemorar": "Dia do Revendedor Lotérico" },
  { "Data": "26/05", "Comemorar": "Dia Nacional de Combate ao Glaucoma" },
  { "Data": "26/05", "Comemorar": "Dia de São Filipe Néri" },
  {
    "Data": "26/05",
    "Comemorar": "Dia da Conscientização sobre a Hanseníase (PR)"
  },
  { "Data": "26/05", "Comemorar": "Dia de Nossa Senhora de Caravaggio (SC)" },
  { "Data": "26/05", "Comemorar": "Dia da Comunicação Batista em 2024" },
  { "Data": "27/05", "Comemorar": "Dia do Profissional Liberal" },
  { "Data": "27/05", "Comemorar": "Dia Nacional da Mata Atlântica" },
  { "Data": "28/05", "Comemorar": "Dia do Ceramista" },
  { "Data": "28/05", "Comemorar": "Dia do Hambúrguer" },
  {
    "Data": "28/05",
    "Comemorar": "Dia Nacional e Internacional de Redução da Mortalidade Materna"
  },
  { "Data": "29/05", "Comemorar": "Dia do Estatístico" },
  { "Data": "29/05", "Comemorar": "Dia do Geógrafo" },
  {
    "Data": "29/05",
    "Comemorar": "Dia Internacional dos Mantenedores da Paz das Nações Unidas"
  },
  { "Data": "29/05", "Comemorar": "Dia do Sociólogo" },
  { "Data": "29/05", "Comemorar": "Dia Mundial da Energia" },
  { "Data": "29/05", "Comemorar": "Dia mundial do desafio em 2024" },
  { "Data": "29/05", "Comemorar": "Dia mundial da Esclerose Múltipla em 2024" },
  { "Data": "29/05", "Comemorar": "Dia Nacional do Censo Escolar em 2024" },
  { "Data": "30/05", "Comemorar": "Dia das Bandeirantes" },
  { "Data": "30/05", "Comemorar": "Dia do Geólogo" },
  { "Data": "30/05", "Comemorar": "Dia da Decoração" },
  {
    "Data": "30/05",
    "Comemorar": "Dia do Movimento das Donas de Casa e dos Consumidores (RS)"
  },
  { "Data": "30/05", "Comemorar": "Corpus Christi em 2024" },
  { "Data": "31/05", "Comemorar": "Dia Internacional da Aeromoça" },
  { "Data": "31/05", "Comemorar": "Dia Mundial sem Tabaco" },
  { "Data": "31/05", "Comemorar": "Dia da Juventude Luterana do Brasil" },
  { "Data": "31/05", "Comemorar": "Dia de Frei Damião (PE)" },
  { "Data": "01/06", "Comemorar": "Dia Internacional da Criança" },
  { "Data": "01/06", "Comemorar": "Dia do Carroceiro (PI)" },
  { "Data": "01/06", "Comemorar": "Dia Mundial do Dinossauro" },
  { "Data": "02/06", "Comemorar": "Dia da Comunidade Italiana - SP" },
  { "Data": "02/06", "Comemorar": "Dia internacional da Prostituta" },
  { "Data": "02/06", "Comemorar": "Dia do Homem Batista em 2024" },
  { "Data": "03/06", "Comemorar": "Dia do Divino" },
  { "Data": "03/06", "Comemorar": "Dia do Profissional de Recursos Humanos" },
  {
    "Data": "04/06",
    "Comemorar": "Dia Internacional das Crianças Inocentes Vitimas de Agressão"
  },
  { "Data": "05/06", "Comemorar": "Dia Internacional da Ecologia" },
  { "Data": "05/06", "Comemorar": "Dia do Pedestre (SP)" },
  {
    "Data": "05/06",
    "Comemorar": "Início da Semana Estadual da Carona Solidária (CE)"
  },
  { "Data": "06/06", "Comemorar": "Dia Nacional do Teste do Pezinho" },
  { "Data": "06/06", "Comemorar": "Dia de São Norberto" },
  { "Data": "06/06", "Comemorar": "International Beatles Fan Day" },
  { "Data": "07/06", "Comemorar": "Dia Nacional da Liberdade de Imprensa" },
  {
    "Data": "07/06",
    "Comemorar": "Dia Nacional dos Catadores de Materiais Recicláveis"
  },
  { "Data": "07/06", "Comemorar": "Dia Mundial da Segurança dos Alimentos" },
  { "Data": "08/06", "Comemorar": "Dia do Citricultor" },
  { "Data": "08/06", "Comemorar": "Dia Mundial dos Oceanos" },
  { "Data": "09/06", "Comemorar": "Dia do Pão" },
  { "Data": "09/06", "Comemorar": "Dia do Porteiro" },
  { "Data": "09/06", "Comemorar": "Dia Internacional do Tenista" },
  { "Data": "09/06", "Comemorar": "Dia do Pastor em 2024" },
  { "Data": "10/06", "Comemorar": "Dia da Língua Portuguesa" },
  { "Data": "10/06", "Comemorar": "Dia de Portugal" },
  { "Data": "11/06", "Comemorar": "Dia da Marinha Brasileira" },
  { "Data": "11/06", "Comemorar": "Dia do Educador Sanitário" },
  { "Data": "11/06", "Comemorar": "Dia de São Barnabé" },
  { "Data": "12/06", "Comemorar": "Dia dos Namorados" },
  { "Data": "12/06", "Comemorar": "Dia do Correio Aéreo Nacional" },
  { "Data": "12/06", "Comemorar": "Dia da Aviação de Transporte" },
  {
    "Data": "12/06",
    "Comemorar": "Dia Internacional de Combate ao Trabalho Infantil"
  },
  {
    "Data": "12/06",
    "Comemorar": "Dia da Consciência da Cardiopatia Congênita (CE)"
  },
  { "Data": "13/06", "Comemorar": "Dia Nacional do Turista" },
  { "Data": "13/06", "Comemorar": "Dia de Santo Antônio" },
  {
    "Data": "13/06",
    "Comemorar": "Dia Internacional do Albino - International Albinism Awareness Day"
  },
  { "Data": "14/06", "Comemorar": "Dia Universal de Deus" },
  { "Data": "14/06", "Comemorar": "Dia de Santo Eliseu" },
  { "Data": "14/06", "Comemorar": "Dia da Manicure (SP)" },
  { "Data": "15/06", "Comemorar": "Dia do Paleontólogo" },
  { "Data": "15/06", "Comemorar": "Dia Mundial da Energia Eólica" },
  {
    "Data": "15/06",
    "Comemorar": "Dia Mundial de Conscientização da Violência Contra a Pessoa Idosa"
  },
  { "Data": "16/06", "Comemorar": "Dia da Unidade Nacional" },
  { "Data": "16/06", "Comemorar": "Dia Internacional da Tartaruga Marinha" },
  { "Data": "17/06", "Comemorar": "Dia de São Manuel" },
  {
    "Data": "17/06",
    "Comemorar": "Dia Mundial do Combate a Seca e Desertificação"
  },
  {
    "Data": "17/06",
    "Comemorar": "Dia da Medicina Veterinária no Exército Brasileiro"
  },
  { "Data": "18/06", "Comemorar": "Dia do Imigrante Japonês" },
  { "Data": "18/06", "Comemorar": "Dia do Químico" },
  {
    "Data": "18/06",
    "Comemorar": "Dia Internacional de Combate ao Discurso de Ódio"
  },
  { "Data": "19/06", "Comemorar": "Dia do Cinema Nacional" },
  { "Data": "20/06", "Comemorar": "Dia Mundial do Refugiado" },
  { "Data": "20/06", "Comemorar": "Dia do Revendedor" },
  { "Data": "20/06", "Comemorar": "Dia de São Adalberto" },
  { "Data": "21/06", "Comemorar": "Dia do Intelectual" },
  { "Data": "21/06", "Comemorar": "Dia Nacional do Combate à Asma" },
  { "Data": "21/06", "Comemorar": "Dia da Juventude Católica" },
  { "Data": "21/06", "Comemorar": "Dia Internacional da Ioga" },
  { "Data": "21/06", "Comemorar": "Início do inverno no hemisfério sul" },
  { "Data": "21/06", "Comemorar": "Início do verão no hemisfério norte" },
  { "Data": "22/06", "Comemorar": "Dia do Aeroviário" },
  { "Data": "23/06", "Comemorar": "Dia do Atleta Olímpico" },
  { "Data": "23/06", "Comemorar": "Dia do Lavrador" },
  { "Data": "23/06", "Comemorar": "Dia Nacional do Agente Marítimo" },
  { "Data": "23/06", "Comemorar": "Dia do Desporto" },
  { "Data": "24/06", "Comemorar": "Dia do Caboclo" },
  { "Data": "24/06", "Comemorar": "Dia de São João" },
  { "Data": "24/06", "Comemorar": "Dia da Aviação de Reconhecimento" },
  { "Data": "24/06", "Comemorar": "Dia Internacional do Leite" },
  { "Data": "24/06", "Comemorar": "Dia do Disco Voador" },
  { "Data": "25/06", "Comemorar": "Dia do Quilo" },
  { "Data": "25/06", "Comemorar": "Dia do Imigrante" },
  { "Data": "25/06", "Comemorar": "Dia Mundial do Vitiligo" },
  { "Data": "26/06", "Comemorar": "Dia de São Vigílio" },
  {
    "Data": "26/06",
    "Comemorar": "Dia Nacional e Internacional de Combate às Drogas"
  },
  { "Data": "26/06", "Comemorar": "Dia do Missionário Batista" },
  { "Data": "26/06", "Comemorar": "Dia do Professor de Geografia" },
  { "Data": "27/06", "Comemorar": "Dia do Artista Lírico" },
  { "Data": "27/06", "Comemorar": "Dia Nacional do Vôlei" },
  { "Data": "27/06", "Comemorar": "Dia Estadual do Quadrilheiro Junino (PE)" },
  { "Data": "28/06", "Comemorar": "Dia de Santo Irineu" },
  { "Data": "28/06", "Comemorar": "Dia Internacional do Orgulho Gay" },
  { "Data": "29/06", "Comemorar": "Dia da Telefonista" },
  { "Data": "29/06", "Comemorar": "Dia do Pescador" },
  { "Data": "29/06", "Comemorar": "Dia de São Pedro" },
  { "Data": "29/06", "Comemorar": "Dia do Chaveiro" },
  { "Data": "30/06", "Comemorar": "Dia do Caminhoneiro" },
  {
    "Data": "30/06",
    "Comemorar": "Dia Estadual do Resgate das Crianças Desaparecidas (PR)"
  },
  {
    "Data": "30/06",
    "Comemorar": "Dia dos Primeiros Mártires da Igreja de Roma"
  },
  { "Data": "30/06", "Comemorar": "Dia Internacional dos Asteroides " },
  { "Data": "01/07", "Comemorar": "Dia da Vacina BCG" },
  { "Data": "02/07", "Comemorar": "Dia Nacional dos Hospitais" },
  { "Data": "02/07", "Comemorar": "Dia do Bombeiro Brasileiro" },
  { "Data": "02/07", "Comemorar": "Independência da Bahia" },
  { "Data": "03/07", "Comemorar": "Dia de São Tomé" },
  { "Data": "03/07", "Comemorar": "Dia dos Incrédulos" },
  {
    "Data": "03/07",
    "Comemorar": "Dia Nacional do Combate à Discriminação Racial"
  },
  { "Data": "03/07", "Comemorar": "Dia do Juiz de Paz" },
  { "Data": "04/07", "Comemorar": "Dia do Atendente de Telemarketing" },
  { "Data": "04/07", "Comemorar": "Dia da Independência dos E.U.A." },
  { "Data": "04/07", "Comemorar": "Dia de Santa Isabel de Portugal" },
  { "Data": "05/07", "Comemorar": "Dia da Independência da Venezuela" },
  { "Data": "05/07", "Comemorar": "Dia do Biquíni" },
  { "Data": "06/07", "Comemorar": "Dia de Santa Maria Goretti" },
  { "Data": "06/07", "Comemorar": "Dia Estadual da Fauna (RJ)" },
  { "Data": "06/07", "Comemorar": "National Air Traffic Control Day" },
  {
    "Data": "06/07",
    "Comemorar": "Dia internacional do cooperativismo em 2024"
  },
  { "Data": "07/07", "Comemorar": "Dia São Panteno" },
  { "Data": "07/07", "Comemorar": "Dia Municipal do Taxista - SP" },
  { "Data": "07/07", "Comemorar": "Dia Mundial do Chocolate" },
  { "Data": "08/07", "Comemorar": "Dia do Padeiro" },
  { "Data": "08/07", "Comemorar": "Dia Mundial da Alergia" },
  { "Data": "08/07", "Comemorar": "Emancipação Política de Sergipe" },
  { "Data": "08/07", "Comemorar": "Dia Nacional do Pesquisador" },
  { "Data": "09/07", "Comemorar": "Dia da Juventude" },
  { "Data": "09/07", "Comemorar": "Dia Internacional pelo Desarmamento" },
  {
    "Data": "09/07",
    "Comemorar": "Dia da Revolução e do Soldado Constitucionalista em São Paulo"
  },
  { "Data": "10/07", "Comemorar": "Dia Mundial da Lei" },
  { "Data": "10/07", "Comemorar": "Dia da Pizza (SP)" },
  { "Data": "10/07", "Comemorar": "Dia da Saúde Ocular" },
  { "Data": "10/07", "Comemorar": "Dia do Engenheiro de Minas" },
  { "Data": "11/07", "Comemorar": "Dia Mundial da População" },
  { "Data": "11/07", "Comemorar": "Dia de São Bento" },
  { "Data": "11/07", "Comemorar": "Dia Internacional do El Mojito" },
  { "Data": "12/07", "Comemorar": "Dia do Engenheiro Florestal" },
  { "Data": "12/07", "Comemorar": "Dia da Igreja Unida (SP)" },
  { "Data": "12/07", "Comemorar": "Dia da Fitoterapia (SC)" },
  { "Data": "12/07", "Comemorar": "Día de la Literatura Caribeña" },
  { "Data": "13/07", "Comemorar": "Dia do Engenheiro Sanitarista" },
  { "Data": "13/07", "Comemorar": "Dia Mundial do Rock" },
  { "Data": "13/07", "Comemorar": "Dia Estadual do Conselho Tutelar (RJ)" },
  { "Data": "13/07", "Comemorar": "Dia dos Atletas Masters (SP)" },
  { "Data": "14/07", "Comemorar": "Dia Mundial da Liberdade" },
  { "Data": "14/07", "Comemorar": "Dia Mundial dos Hospitais" },
  { "Data": "14/07", "Comemorar": "Dia Nacional dos Povos Americanos" },
  { "Data": "14/07", "Comemorar": "Comemoração da Queda da Bastilha" },
  { "Data": "15/07", "Comemorar": "Dia Nacional dos Clubes" },
  { "Data": "15/07", "Comemorar": "Dia Internacional do Homem" },
  { "Data": "16/07", "Comemorar": "Dia de Nossa Senhora do Carmo" },
  { "Data": "16/07", "Comemorar": "Dia Nacional do Comerciante" },
  { "Data": "17/07", "Comemorar": "Dia de Proteção às Florestas" },
  { "Data": "17/07", "Comemorar": "Dia do Submarinista" },
  { "Data": "17/07", "Comemorar": "Dia Mundial do Emoji" },
  { "Data": "18/07", "Comemorar": "Dia Nacional do Trovador" },
  { "Data": "18/07", "Comemorar": "Dia Internacional Nelson Mandela" },
  { "Data": "18/07", "Comemorar": "Dia de Luta Contra o Câncer de Mama (RS)" },
  { "Data": "18/07", "Comemorar": "Dia dos Veteranos de Guerra" },
  { "Data": "19/07", "Comemorar": "Dia da Caridade" },
  { "Data": "19/07", "Comemorar": "Dia do Futebol" },
  { "Data": "19/07", "Comemorar": "Dia dos Povos Oprimidos" },
  { "Data": "19/07", "Comemorar": "Dia da Junta Comercial " },
  { "Data": "20/07", "Comemorar": "Dia Internacional do Amigo" },
  { "Data": "20/07", "Comemorar": "Dia do Amigo" },
  { "Data": "20/07", "Comemorar": "Dia do Tatuador" },
  { "Data": "20/07", "Comemorar": "Dia do Peão de Rodeio (GO)" },
  { "Data": "20/07", "Comemorar": "International Chess Day" },
  { "Data": "20/07", "Comemorar": "International Cake Day" },
  { "Data": "21/07", "Comemorar": "Dia de São Lourenço de Brindisi" },
  { "Data": "21/07", "Comemorar": "Dia do Jornal Batista em 2024" },
  { "Data": "22/07", "Comemorar": "Dia de Santa Maria Madalena" },
  { "Data": "22/07", "Comemorar": "Início da Semana da Agricultura" },
  { "Data": "22/07", "Comemorar": "Dia Mundial do Cérebro" },
  { "Data": "23/07", "Comemorar": "Dia do Guarda Rodoviário" },
  { "Data": "23/07", "Comemorar": "Dia de Santa Brígida" },
  { "Data": "24/07", "Comemorar": "Dia do Calouro" },
  { "Data": "24/07", "Comemorar": "Dia de Santa Cristina" },
  { "Data": "24/07", "Comemorar": "Dia Nacional do Suinocultor" },
  { "Data": "25/07", "Comemorar": "Dia Nacional da Agricultura" },
  { "Data": "25/07", "Comemorar": "Dia dos Viajantes" },
  { "Data": "25/07", "Comemorar": "Dia Internacional da Mulher Negra" },
  {
    "Data": "25/07",
    "Comemorar": "Dia Nacional de Tereza de Benguela e da Mulher Negra"
  },
  { "Data": "25/07", "Comemorar": "Dia do Colono" },
  { "Data": "25/07", "Comemorar": "Dia do Escritor" },
  { "Data": "25/07", "Comemorar": "Dia de São Cristóvão" },
  { "Data": "26/07", "Comemorar": "Dia dos Avós" },
  { "Data": "26/07", "Comemorar": "Dia de Santana e São Joaquim" },
  { "Data": "27/07", "Comemorar": "Dia do Motociclista" },
  {
    "Data": "27/07",
    "Comemorar": "Dia Mundial de Combate ao Câncer de Cabeça e Pescoço"
  },
  { "Data": "27/07", "Comemorar": "Dia da Pediatria" },
  { "Data": "28/07", "Comemorar": "Dia do Agricultor" },
  {
    "Data": "28/07",
    "Comemorar": "Dia Mundial de Luta contra as Hepatites Virais"
  },
  { "Data": "29/07", "Comemorar": "Dia de Santa Marta" },
  { "Data": "29/07", "Comemorar": "Dia da Lasanha" },
  { "Data": "30/07", "Comemorar": "Dia de São Pedro Crisólogo" },
  {
    "Data": "30/07",
    "Comemorar": "Día de los mártires de la Revolución (Cuba)"
  },
  { "Data": "31/07", "Comemorar": "Dia de Santo Inácio de Loyola" },
  { "Data": "31/07", "Comemorar": "Dia Mundial do Orgasmo" },
  { "Data": "01/08", "Comemorar": "Dia Nacional do Selo Postal Brasileiro" },
  { "Data": "01/08", "Comemorar": "Dia do Cerealista" },
  { "Data": "01/08", "Comemorar": "Dia Estadual do Maracatu (PE)" },
  { "Data": "02/08", "Comemorar": "Dia Universal do Folclore" },
  { "Data": "02/08", "Comemorar": "Dia Estadual do Nordestino - SP" },
  { "Data": "02/08", "Comemorar": "Dia de Santo Euzébio" },
  { "Data": "03/08", "Comemorar": "Dia do Tintureiro" },
  { "Data": "03/08", "Comemorar": "Dia do Quadro de Engenheiros Militares" },
  { "Data": "03/08", "Comemorar": "Dia de Santa Lídia" },
  { "Data": "04/08", "Comemorar": "Dia do Padre" },
  { "Data": "04/08", "Comemorar": "Dia de São João Maria Vianney" },
  { "Data": "05/08", "Comemorar": "Dia Nacional da Saúde" },
  { "Data": "05/08", "Comemorar": "Dia da Cultura Caipira (SP)" },
  { "Data": "05/08", "Comemorar": "Dia Nacional da Vigilância Sanitária" },
  { "Data": "05/08", "Comemorar": "International Beer Day" },
  { "Data": "06/08", "Comemorar": "Dia da Independência da Bolívia" },
  { "Data": "07/08", "Comemorar": "Dia de São Caetano" },
  { "Data": "07/08", "Comemorar": "Dia Estadual da Saúde Mental - RS" },
  { "Data": "08/08", "Comemorar": "Dia Nacional do Combate ao Colesterol" },
  { "Data": "08/08", "Comemorar": "Dia Estadual do Sindicalista - RJ" },
  { "Data": "08/08", "Comemorar": "Dia de São Domingos" },
  { "Data": "08/08", "Comemorar": "Dia Mundial do Pedestre" },
  { "Data": "08/08", "Comemorar": "World Cat-Day ou Internation Cat-Day" },
  { "Data": "09/08", "Comemorar": "Dia Internacional dos Povos Indígenas" },
  { "Data": "09/08", "Comemorar": "Dia de São Fábio" },
  { "Data": "09/08", "Comemorar": "Dia do Líder Comunitário (CE)" },
  {
    "Data": "09/08",
    "Comemorar": "Dia Estadual da Mobilização pela Vida (MT)"
  },
  { "Data": "09/08", "Comemorar": "Dia Distrital da Equoterapia (DF)" },
  { "Data": "09/08", "Comemorar": "Dia de Ação Contra a Dengue (PR)" },
  { "Data": "09/08", "Comemorar": "Dia da Família Paulista" },
  { "Data": "09/08", "Comemorar": "Dia Internacional do Coworking" },
  { "Data": "10/08", "Comemorar": "Dia de São Lourenço" },
  { "Data": "11/08", "Comemorar": "Dia do Advogado" },
  { "Data": "11/08", "Comemorar": "Dia da Consciência Nacional" },
  { "Data": "11/08", "Comemorar": "Dia de Santa Clara de Assis" },
  { "Data": "11/08", "Comemorar": "Dia dos pais em 2024" },
  { "Data": "12/08", "Comemorar": "Dia Nacional das Artes" },
  { "Data": "12/08", "Comemorar": "Dia do Presbiterianismo Nacional" },
  { "Data": "13/08", "Comemorar": "Dia do Economista" },
  { "Data": "13/08", "Comemorar": "Dia do Médico Psiquiatra" },
  { "Data": "13/08", "Comemorar": "Dia Internacional dos Canhotos" },
  { "Data": "14/08", "Comemorar": "Dia do Combate à Poluição" },
  { "Data": "14/08", "Comemorar": "Dia de São Maximiliano Maria Kolbe" },
  { "Data": "14/08", "Comemorar": "Dia do Cardiologista" },
  { "Data": "15/08", "Comemorar": "Dia Mundial do Fotógrafo" },
  { "Data": "15/08", "Comemorar": "Dia do Solteiro" },
  { "Data": "15/08", "Comemorar": "Dia da Informática" },
  { "Data": "15/08", "Comemorar": "Dia da Gestante" },
  { "Data": "16/08", "Comemorar": "Aniversário da cidade de Teresina - PI" },
  { "Data": "16/08", "Comemorar": "Dia do Filósofo" },
  { "Data": "16/08", "Comemorar": "Debian Day" },
  { "Data": "17/08", "Comemorar": "Dia do Patrimônio Histórico" },
  { "Data": "17/08", "Comemorar": "Dia do Pão de Queijo" },
  { "Data": "18/08", "Comemorar": "Dia de Santa Helena" },
  { "Data": "18/08", "Comemorar": "Dia Estadual da Siderurgia - MG" },
  { "Data": "18/08", "Comemorar": "Dia Municipal do Motoqueiro - CE" },
  { "Data": "18/08", "Comemorar": "Dia da Revolução Cultural" },
  { "Data": "18/08", "Comemorar": "Dia do Estagiário" },
  { "Data": "19/08", "Comemorar": "Dia do Artista de Teatro" },
  { "Data": "19/08", "Comemorar": "Dia do Historiador" },
  { "Data": "19/08", "Comemorar": "Dia Nacional do Ciclista" },
  { "Data": "19/08", "Comemorar": "Dia Mundial da Fotografia" },
  { "Data": "19/08", "Comemorar": "Dia Internacional da Ajuda Humanitária" },
  { "Data": "20/08", "Comemorar": "Dia do Maçom" },
  { "Data": "21/08", "Comemorar": "Dia do Favelado" },
  { "Data": "21/08", "Comemorar": "Dia do São Pio X" },
  { "Data": "22/08", "Comemorar": "Dia Nacional do Folclore" },
  { "Data": "22/08", "Comemorar": "Dia da Nossa Senhora Rainha" },
  { "Data": "22/08", "Comemorar": "Dia do Educador Especial" },
  { "Data": "23/08", "Comemorar": "Dia do Aviador Naval" },
  { "Data": "23/08", "Comemorar": "Dia de Luta Contra a Injustiça" },
  { "Data": "23/08", "Comemorar": "Dia da Intendência" },
  { "Data": "23/08", "Comemorar": "Dia de Santa Rosa de Lima" },
  { "Data": "24/08", "Comemorar": "Dia dos Artistas" },
  { "Data": "24/08", "Comemorar": "Dia Nacional da Comunidade Ucraniana" },
  { "Data": "24/08", "Comemorar": "Dia da infância" },
  { "Data": "25/08", "Comemorar": "Dia do Soldado" },
  { "Data": "26/08", "Comemorar": "Dia da Declaração dos Direitos do Homem" },
  { "Data": "26/08", "Comemorar": "Aniversário de Campo Grande - MS" },
  { "Data": "27/08", "Comemorar": "Dia do Psicólogo" },
  { "Data": "27/08", "Comemorar": "Dia Municipal da Limpeza Urbana - MG" },
  { "Data": "27/08", "Comemorar": "Dia de Santa Mônica" },
  { "Data": "27/08", "Comemorar": "Dia do Corretor de Imóveis  " },
  { "Data": "28/08", "Comemorar": "Dia Nacional dos Bancários" },
  { "Data": "28/08", "Comemorar": "Dia de Santo Agostinho" },
  {
    "Data": "28/08",
    "Comemorar": "Dia Estadual dos Bancários e Financiários (PI)"
  },
  { "Data": "29/08", "Comemorar": "Dia Nacional do Combate ao Fumo" },
  { "Data": "29/08", "Comemorar": "Dia do Gamer" },
  { "Data": "29/08", "Comemorar": "Dia Nacional da Visibilidade Lésbica" },
  { "Data": "29/08", "Comemorar": "Dia Internacional contra Testes Nucleares" },
  { "Data": "30/08", "Comemorar": "Dia do Vendedor Lojista" },
  { "Data": "30/08", "Comemorar": "Dia Internacional dos Desaparecidos" },
  {
    "Data": "30/08",
    "Comemorar": "Dia Nacional de Conscientização da Esclerose Múltipla"
  },
  { "Data": "31/08", "Comemorar": "Dia do Nutricionista" },
  { "Data": "31/08", "Comemorar": "Dia Internacional do Blog" },
  { "Data": "31/08", "Comemorar": "Dia das Estrelas do Oriente (SP)" },
  { "Data": "01/09", "Comemorar": "Dia do Caixeiro Viajante" },
  { "Data": "01/09", "Comemorar": "Dia de Santa Beatriz" },
  { "Data": "01/09", "Comemorar": "Dia do Profissional de Educação Física" },
  {
    "Data": "01/09",
    "Comemorar": "Dia Mundial de Oração pelo Cuidado pela Criação"
  },
  {
    "Data": "02/09",
    "Comemorar": "Dia do Repórter Fotográfico e Cinematográfico"
  },
  { "Data": "02/09", "Comemorar": "Dia do Florista" },
  { "Data": "03/09", "Comemorar": "Dia do Biólogo" },
  { "Data": "04/09", "Comemorar": "Dia do Serventuário" },
  { "Data": "05/09", "Comemorar": "Dia do Oficial de Farmácia" },
  { "Data": "05/09", "Comemorar": "Dia do Oficial de Justiça" },
  { "Data": "05/09", "Comemorar": "Dia do Irmão" },
  { "Data": "05/09", "Comemorar": "Dia da beata Teresa de Calcutá" },
  { "Data": "05/09", "Comemorar": "Dia Internacional da Caridade" },
  { "Data": "05/09", "Comemorar": "Dia dos Irmãos" },
  { "Data": "05/09", "Comemorar": "Dia da Amazônia" },
  {
    "Data": "06/09",
    "Comemorar": "Dia do Cabeleireiro (também comemorado em 19/01)"
  },
  { "Data": "06/09", "Comemorar": "Dia do Sexo" },
  { "Data": "06/09", "Comemorar": "Dia do Alfaiate" },
  { "Data": "07/09", "Comemorar": "Dia da Pátria do Brasil" },
  { "Data": "07/09", "Comemorar": "Dia de Santa Regina" },
  { "Data": "07/09", "Comemorar": "Dia de São Clodoaldo" },
  { "Data": "08/09", "Comemorar": "Dia Mundial da Alfabetização" },
  { "Data": "08/09", "Comemorar": "Festa da Natividade de Nossa Senhora" },
  { "Data": "08/09", "Comemorar": "Dia Nacional da Luta por Medicamentos" },
  { "Data": "08/09", "Comemorar": "Dia Mundial da Fibrose Cística" },
  {
    "Data": "08/09",
    "Comemorar": "Aniversário da cidade de São Luís do Maranhão"
  },
  { "Data": "08/09", "Comemorar": "Dia da Virgen de la Caridad del Cobre" },
  {
    "Data": "08/09",
    "Comemorar": "Dia da Comunidade Gebelinense (SP) em 2024"
  },
  {
    "Data": "08/09",
    "Comemorar": "Dia da Família Afro-Brasileira (SP) em 2024"
  },
  { "Data": "08/09", "Comemorar": "Dia da Mulher Evangélica (MA) em 2024" },
  { "Data": "08/09", "Comemorar": "Dia Estadual do Mecânico (SC) em 2024" },
  { "Data": "08/09", "Comemorar": "Dia da Memória Pet em 2024" },
  { "Data": "09/09", "Comemorar": "Dia do Administrador" },
  { "Data": "09/09", "Comemorar": "Dia da Velocidade" },
  { "Data": "09/09", "Comemorar": "Dia do Médico Veterinário" },
  { "Data": "09/09", "Comemorar": "Dia do Técnico em Administração" },
  { "Data": "09/09", "Comemorar": "Dia do Hot Dog" },
  { "Data": "10/09", "Comemorar": "Dia do Gordo" },
  { "Data": "10/09", "Comemorar": "Dia de Luta contra a Gordofobia" },
  { "Data": "10/09", "Comemorar": "Dia Mundial de Prevenção ao Suicídio" },
  { "Data": "10/09", "Comemorar": "Dia de São Nicolau de Tolentino" },
  { "Data": "11/09", "Comemorar": "Dia do Árbitro Esportivo" },
  { "Data": "11/09", "Comemorar": "Dia Nacional do Cerrado" },
  { "Data": "11/09", "Comemorar": "Dia do Brigadeiro" },
  { "Data": "12/09", "Comemorar": "Dia Nacional da Recreação" },
  { "Data": "12/09", "Comemorar": "Dia do trator" },
  { "Data": "13/09", "Comemorar": "Dia Mundial do Agrônomo" },
  { "Data": "13/09", "Comemorar": "Dia da Cachaça" },
  { "Data": "13/09", "Comemorar": "Dia de São João Crisóstomo" },
  { "Data": "13/09", "Comemorar": "Dia Mundial da Sepse" },
  { "Data": "14/09", "Comemorar": "Dia da Exaltação da Santa Cruz" },
  { "Data": "14/09", "Comemorar": "Dia do Frevo" },
  { "Data": "14/09", "Comemorar": "Dia do Guarda Civil Metropolitano" },
  { "Data": "14/09", "Comemorar": "Dia do Operador de Redes Telefônicas" },
  { "Data": "14/09", "Comemorar": "Dia do Cavalo (RS)" },
  {
    "Data": "14/09",
    "Comemorar": "Dia Mundial da Realidade Climática (Worldwide Climate Reality)"
  },
  {
    "Data": "14/09",
    "Comemorar": "Dia Municipal da Longevidade Saudável (RJ)"
  },
  { "Data": "14/09", "Comemorar": "Dia do Surf (SP)" },
  { "Data": "14/09", "Comemorar": "Dia da Comunidade Muçulmana" },
  { "Data": "14/09", "Comemorar": "Dia Estadual do Jiu-Jitsu (PA)" },
  { "Data": "14/09", "Comemorar": "Dia Internacional da Capivara" },
  {
    "Data": "14/09",
    "Comemorar": "Dia Mundial dos Primeiros-Socorros em 2024"
  },
  { "Data": "15/09", "Comemorar": "Dia do Musicoterapeuta" },
  { "Data": "15/09", "Comemorar": "Dia de Nossa Senhora das Dores" },
  { "Data": "15/09", "Comemorar": "Dia do Cliente" },
  { "Data": "15/09", "Comemorar": "Dia Mundial do Linfoma" },
  { "Data": "16/09", "Comemorar": "Dia da Independência do México" },
  { "Data": "16/09", "Comemorar": "Dia Nacional do Caminhoneiro" },
  { "Data": "16/09", "Comemorar": "Emancipação Política de Alagoas" },
  {
    "Data": "16/09",
    "Comemorar": "Dia Internacional para a Preservação da Camada de Ozônio"
  },
  { "Data": "17/09", "Comemorar": "Dia da Compreensão Mundial" },
  { "Data": "18/09", "Comemorar": "Dia dos Símbolos Nacionais" },
  { "Data": "18/09", "Comemorar": "Dia de São José de Cupertino" },
  { "Data": "18/09", "Comemorar": "Início da Semana Nacional de Trânsito" },
  { "Data": "19/09", "Comemorar": "Dia do Comprador" },
  { "Data": "19/09", "Comemorar": "Dia do Ortopedista" },
  {
    "Data": "19/09",
    "Comemorar": "Dia Estadual do Profissional Pedagogo (MT)"
  },
  { "Data": "19/09", "Comemorar": "Dia Estadual do Chamamé (MS)" },
  { "Data": "19/09", "Comemorar": "Dia da Agropecuária (PR)" },
  {
    "Data": "19/09",
    "Comemorar": "Dia da Mobilização Social pela Educação (GO)"
  },
  { "Data": "19/09", "Comemorar": "Dia do Adolescente (SP)" },
  { "Data": "19/09", "Comemorar": "Dia do Educador Social (CE)" },
  {
    "Data": "19/09",
    "Comemorar": "Dia Estadual dos Jovens Adventistas do Sétimo Dia (ES)"
  },
  { "Data": "19/09", "Comemorar": "Dia de São Januário" },
  { "Data": "20/09", "Comemorar": "Dia do Gaúcho" },
  { "Data": "20/09", "Comemorar": "Dia da Revolução Farroupilha" },
  {
    "Data": "20/09",
    "Comemorar": "Dia da Proclamação da República Rio-Grandense"
  },
  { "Data": "20/09", "Comemorar": "Dia do Pombo da Paz" },
  { "Data": "20/09", "Comemorar": "Dia do Funcionário Municipal" },
  { "Data": "21/09", "Comemorar": "Dia da Árvore" },
  { "Data": "21/09", "Comemorar": "Dia Internacional da Paz" },
  { "Data": "21/09", "Comemorar": "Dia do Fazendeiro" },
  { "Data": "21/09", "Comemorar": "Dia do Radialista" },
  { "Data": "21/09", "Comemorar": "Dia de São Mateus Evangelista" },
  {
    "Data": "21/09",
    "Comemorar": "Dia Nacional de Luta das Pessoas Deficientes"
  },
  { "Data": "21/09", "Comemorar": "Dia Mundial da Doença de Alzheimer" },
  {
    "Data": "21/09",
    "Comemorar": "Dia do Segurado do Município de Porto Alegre"
  },
  { "Data": "21/09", "Comemorar": "Início da primavera no hemisfério sul" },
  { "Data": "21/09", "Comemorar": "Início do outono no hemisfério norte" },
  { "Data": "21/09", "Comemorar": "Dia Mundial de Limpeza do Litoral em 2024" },
  { "Data": "22/09", "Comemorar": "Dia Nacional da Defesa da Fauna" },
  {
    "Data": "22/09",
    "Comemorar": "Dia Mundial Sem Carro (World Car Free Day)"
  },
  { "Data": "22/09", "Comemorar": "Dia do Contador" },
  { "Data": "22/09", "Comemorar": "Dia da Banana" },
  { "Data": "22/09", "Comemorar": "Dia Nacional do Atleta Paraolímpico" },
  { "Data": "22/09", "Comemorar": "Dia Mundial da Leucemia Mieloide Crônica" },
  { "Data": "22/09", "Comemorar": "Dia de São Maurício" },
  { "Data": "22/09", "Comemorar": "Dia dos Amantes" },
  { "Data": "22/09", "Comemorar": "Dia Mundial do coração em 2024" },
  { "Data": "22/09", "Comemorar": "Dia Mundial do surdo em 2024" },
  { "Data": "23/09", "Comemorar": "Dia do Técnico Industrial" },
  { "Data": "23/09", "Comemorar": "Dia do Técnico em Edificações" },
  { "Data": "23/09", "Comemorar": "Dia de São Lino" },
  { "Data": "23/09", "Comemorar": "Dia do Sorvete" },
  {
    "Data": "23/09",
    "Comemorar": "Dia da Proclamação ao Mundo para a Família em São Paulo"
  },
  { "Data": "23/09", "Comemorar": "Dia de São Pio de Pietrelcina" },
  { "Data": "24/09", "Comemorar": "Dia do Soldador" },
  { "Data": "25/09", "Comemorar": "Dia do Rádio" },
  { "Data": "25/09", "Comemorar": "Dia da Tia Solteirona" },
  {
    "Data": "25/09",
    "Comemorar": "Dia de Luta contra a Ataxia Dominante em Porto Alegre"
  },
  { "Data": "25/09", "Comemorar": "Dia do Auditor da Justiça Desportiva" },
  { "Data": "25/09", "Comemorar": "Término da Semana Nacional de Trânsito" },
  { "Data": "25/09", "Comemorar": "Dia Internacional do Farmacêutico" },
  {
    "Data": "25/09",
    "Comemorar": "Dia Estadual de Prevenção e Enfrentamento ao Crack (BA)"
  },
  { "Data": "26/09", "Comemorar": "Dia do Policial" },
  { "Data": "26/09", "Comemorar": "Dia Nacional do Surdo" },
  { "Data": "26/09", "Comemorar": "Dia de São Cosme e São Damião" },
  { "Data": "26/09", "Comemorar": "Dia Interamericano das Relações Públicas" },
  { "Data": "26/09", "Comemorar": "Dia Marítimo Mundial em 2024" },
  { "Data": "27/09", "Comemorar": "Dia do Ancião" },
  { "Data": "27/09", "Comemorar": "Dia Mundial do Turismo" },
  { "Data": "27/09", "Comemorar": "Dia do Encanador e Instalador Hidráulico" },
  { "Data": "27/09", "Comemorar": "Dia Nacional de Doação de Órgãos" },
  { "Data": "28/09", "Comemorar": "Dia Nacional da Liberdade de Expressão" },
  { "Data": "28/09", "Comemorar": "Dia Mundial de Combate à Raiva" },
  { "Data": "28/09", "Comemorar": "Dia de São Venceslau" },
  { "Data": "28/09", "Comemorar": "Dia do Hidrógrafo" },
  {
    "Data": "28/09",
    "Comemorar": "Día de Lucha por la Despenalización del Aborto en América latina y el Caribe"
  },
  { "Data": "28/09", "Comemorar": "Dia da Mãe Preta" },
  {
    "Data": "28/09",
    "Comemorar": "Dia da Responsabilidade Social do Ensino Superior Particular em 2024"
  },
  { "Data": "29/09", "Comemorar": "Dia do Anunciante" },
  { "Data": "29/09", "Comemorar": "Dia Mundial do Petróleo" },
  {
    "Data": "29/09",
    "Comemorar": "Dia dos Arcanjos - Miguel, Rafael e Gabriel"
  },
  { "Data": "30/09", "Comemorar": "Dia Nacional do Jornaleiro" },
  { "Data": "30/09", "Comemorar": "Dia da Secretária" },
  { "Data": "30/09", "Comemorar": "Dia do Tuberculoso" },
  { "Data": "30/09", "Comemorar": "Dia do Churrasqueiro" },
  { "Data": "30/09", "Comemorar": "Dia da Navegação" },
  { "Data": "30/09", "Comemorar": "Dia Mundial do Tradutor" },
  { "Data": "30/09", "Comemorar": "Dia de São Jerônimo" },
  { "Data": "30/09", "Comemorar": "Dia dos Capelães da Marinha" },
  { "Data": "30/09", "Comemorar": "Dia Internacional da Tradução" },
  { "Data": "01/10", "Comemorar": "Dia Internacional das Pessoas Idosas" },
  { "Data": "01/10", "Comemorar": "Dia do Agente Comercial" },
  { "Data": "01/10", "Comemorar": "Dia Nacional de Doação de Leite Humano" },
  { "Data": "01/10", "Comemorar": "Dia do Representante Comercial" },
  { "Data": "01/10", "Comemorar": "Dia Nacional do Vereador" },
  { "Data": "01/10", "Comemorar": "Dia de Santa Terezinha" },
  { "Data": "01/10", "Comemorar": "Dia Mundial do Vendedor" },
  { "Data": "01/10", "Comemorar": "Dia Mundial do Vegetarianismo" },
  { "Data": "01/10", "Comemorar": "Dia Mundial da Música" },
  { "Data": "01/10", "Comemorar": "Dia Nacional da China" },
  { "Data": "02/10", "Comemorar": "Dia do Notário" },
  {
    "Data": "02/10",
    "Comemorar": "Dia do Quadro Complementar de Oficiais do Exército"
  },
  { "Data": "02/10", "Comemorar": "Dia Nacional do Habitat" },
  { "Data": "02/10", "Comemorar": "Dia do Anjo da Guarda" },
  { "Data": "02/10", "Comemorar": "Dia Internacional da Não-Violência" },
  { "Data": "03/10", "Comemorar": "Dia das Abelhas" },
  { "Data": "03/10", "Comemorar": "Dia do Petróleo Brasileiro" },
  { "Data": "03/10", "Comemorar": "Dia Mundial do Dentista" },
  { "Data": "03/10", "Comemorar": "Dia da Unidade Alemã" },
  { "Data": "04/10", "Comemorar": "Dia Mundial dos Animais" },
  { "Data": "04/10", "Comemorar": "Dia da Natureza" },
  { "Data": "04/10", "Comemorar": "Dia de São Francisco de Assis" },
  {
    "Data": "04/10",
    "Comemorar": "Dia Nacional do Agente Comunitário de Saúde"
  },
  { "Data": "04/10", "Comemorar": "Dia Universal da Anistia" },
  { "Data": "04/10", "Comemorar": "Dia do Pantaneiro" },
  { "Data": "04/10", "Comemorar": "Dia Internacional do Poeta" },
  { "Data": "04/10", "Comemorar": "Dia do Barman" },
  { "Data": "04/10", "Comemorar": "Dia do Cão" },
  { "Data": "05/10", "Comemorar": "Dia Mundial da Habitação" },
  { "Data": "05/10", "Comemorar": "Dia do Morador de Cortiço" },
  { "Data": "05/10", "Comemorar": "Dia do Bóia-Fria" },
  { "Data": "05/10", "Comemorar": "Dia da Micro e Pequena Empresa" },
  { "Data": "06/10", "Comemorar": "Dia Nacional do Circulista" },
  { "Data": "06/10", "Comemorar": "Dia do Tecnólogo" },
  { "Data": "07/10", "Comemorar": "Dia Nacional do Compositor" },
  { "Data": "07/10", "Comemorar": "Dia de Nossa Senhora do Rosário" },
  { "Data": "07/10", "Comemorar": "Dia Internacional do Trabalho Decente" },
  { "Data": "07/10", "Comemorar": "Dia Mundial do Habitat em 2024" },
  { "Data": "08/10", "Comemorar": "Dia do Nordestino" },
  { "Data": "08/10", "Comemorar": "Dia do Asfaltador" },
  { "Data": "08/10", "Comemorar": "Dia pelo Direito a Vida" },
  { "Data": "08/10", "Comemorar": "Dia do Nascituro" },
  { "Data": "09/10", "Comemorar": "Dia do Profissional de Consórcio" },
  { "Data": "09/10", "Comemorar": "Dia do Atletismo" },
  { "Data": "09/10", "Comemorar": "Dia do Açougueiro" },
  {
    "Data": "09/10",
    "Comemorar": "Dia da Normalista e do Normalista (RJ) em 2024"
  },
  { "Data": "09/10", "Comemorar": "Emergency Nurse's Day em 2024" },
  { "Data": "10/10", "Comemorar": "Dia da Honestidade" },
  { "Data": "10/10", "Comemorar": "Dia Mundial do Lions Clube" },
  { "Data": "10/10", "Comemorar": "Dia Mundial da Saúde Mental" },
  { "Data": "10/10", "Comemorar": "Dia dos Inativos da Marinha" },
  { "Data": "11/10", "Comemorar": "Dia do Deficiente Físico" },
  {
    "Data": "11/10",
    "Comemorar": "Dia Internacional da Prevenção à Obesidade"
  },
  { "Data": "11/10", "Comemorar": "Dia Internacional da Menina" },
  {
    "Data": "11/10",
    "Comemorar": "Dia Municipal de Luta por Creches em Porto Alegre - RS"
  },
  { "Data": "11/10", "Comemorar": "Dia Mundial do Ovo em 2024" },
  { "Data": "12/10", "Comemorar": "Dia de Nossa Senhora Aparecida" },
  { "Data": "12/10", "Comemorar": "Dia da Criança" },
  { "Data": "12/10", "Comemorar": "Dia Nacional de Luta por Creches" },
  { "Data": "12/10", "Comemorar": "Dia Nacional da Leitura" },
  { "Data": "12/10", "Comemorar": "Dia dos Corretores de Seguro" },
  { "Data": "12/10", "Comemorar": "Dia do Engenheiro Agrônomo" },
  { "Data": "12/10", "Comemorar": "Dia Batista de Evangelismo Pessoal" },
  { "Data": "12/10", "Comemorar": "Dia Nacional do Lobo-Guará" },
  { "Data": "12/10", "Comemorar": "Día Continental de la Descolonización" },
  { "Data": "12/10", "Comemorar": "Día de la Hispanidad" },
  { "Data": "12/10", "Comemorar": "Festa de Nossa Senhora dos Remédios (PB)" },
  {
    "Data": "12/10",
    "Comemorar": "Dia da Mobilização pela Despoluição das Águas do Rio Tietê (SP)"
  },
  { "Data": "13/10", "Comemorar": "Dia Nacional do Dinheiro" },
  { "Data": "13/10", "Comemorar": "Dia de Santo Eduardo" },
  { "Data": "13/10", "Comemorar": "Dia do Terapeuta Ocupacional" },
  { "Data": "13/10", "Comemorar": "Dia do Fisioterapeuta" },
  { "Data": "13/10", "Comemorar": "Círio de Nazaré em 2024" },
  { "Data": "14/10", "Comemorar": "Dia Nacional da Pecuária" },
  { "Data": "14/10", "Comemorar": "Dia do Jiu-Jitsu em São Paulo" },
  { "Data": "14/10", "Comemorar": "National Dessert Day (EUA)" },
  {
    "Data": "14/10",
    "Comemorar": "Dia Mundial da Padronização (World Standards Day)"
  },
  { "Data": "14/10", "Comemorar": "Día de la Integración Centroamericana" },
  { "Data": "15/10", "Comemorar": "Dia do Professor" },
  { "Data": "15/10", "Comemorar": "Dia Mundial de Lavar as Mãos" },
  { "Data": "15/10", "Comemorar": "Dia de Santa Teresa d`Ávila" },
  { "Data": "15/10", "Comemorar": "Dia do Educador Ambiental" },
  { "Data": "16/10", "Comemorar": "Dia do Anestesista" },
  { "Data": "16/10", "Comemorar": "Dia Mundial da Alimentação" },
  { "Data": "16/10", "Comemorar": "Dia Mundial do Pão" },
  { "Data": "16/10", "Comemorar": "Dia da Ciência e da Tecnologia" },
  { "Data": "16/10", "Comemorar": "Dia de Santa Edwiges" },
  { "Data": "17/10", "Comemorar": "Dia do Eletricista" },
  { "Data": "17/10", "Comemorar": "Dia da Apicultura" },
  {
    "Data": "17/10",
    "Comemorar": "Dia Internacional para a Erradicação da Pobreza"
  },
  { "Data": "17/10", "Comemorar": "Dia do Profissional de Propaganda" },
  { "Data": "17/10", "Comemorar": "Dia Nacional da Música Popular Brasileira" },
  { "Data": "17/10", "Comemorar": "Dia da Indústria Aeronáutica Brasileira" },
  { "Data": "17/10", "Comemorar": "Dia do maquinista - Marinha" },
  { "Data": "18/10", "Comemorar": "Dia do Médico" },
  { "Data": "18/10", "Comemorar": "Dia de São Lucas" },
  { "Data": "18/10", "Comemorar": "Dia do Estivador" },
  { "Data": "19/10", "Comemorar": "Dia Mundial de Combate ao Câncer de Mama" },
  { "Data": "19/10", "Comemorar": "Dia do Guarda-Noturno" },
  { "Data": "19/10", "Comemorar": "Dia de São Paulo da Cruz" },
  { "Data": "19/10", "Comemorar": "Dia do Piauí" },
  { "Data": "19/10", "Comemorar": "Dia do Coralista (SC)" },
  { "Data": "19/10", "Comemorar": "Dia Estadual de Combate ao Crack (ES)" },
  { "Data": "19/10", "Comemorar": "Dia do Profissional de Informática" },
  { "Data": "19/10", "Comemorar": "Dia Nacional de Combate à Sífilis em 2024" },
  {
    "Data": "19/10",
    "Comemorar": "Vídeos Caseiros ('Home Movie Day') em 2024"
  },
  { "Data": "20/10", "Comemorar": "Dia do Poeta" },
  {
    "Data": "20/10",
    "Comemorar": "Dia Internacional do Controlador de Tráfego Aéreo"
  },
  { "Data": "20/10", "Comemorar": "Dia Internacional do Arquivista" },
  { "Data": "20/10", "Comemorar": "Dia do Maquinista Ferroviário" },
  { "Data": "20/10", "Comemorar": "Dia Mundial de Combate ao Bullying" },
  { "Data": "20/10", "Comemorar": "Dia Mundial e Nacional da Osteoporose" },
  { "Data": "21/10", "Comemorar": "Dia da Alimentação na Escola" },
  { "Data": "21/10", "Comemorar": "Dia do Lixeiro" },
  { "Data": "21/10", "Comemorar": "Dia do Ecumenismo" },
  { "Data": "21/10", "Comemorar": "Dia do Contato Publicitário" },
  { "Data": "22/10", "Comemorar": "Dia da Praça" },
  { "Data": "22/10", "Comemorar": "Dia do Paraquedista" },
  { "Data": "22/10", "Comemorar": "Dia Nacional do Enólogo" },
  { "Data": "22/10", "Comemorar": "Dia de São João Paulo II" },
  { "Data": "23/10", "Comemorar": "Dia Nacional do Aviador" },
  { "Data": "23/10", "Comemorar": "Dia da Segurança (PR)" },
  { "Data": "23/10", "Comemorar": "Dia Estadual do Desarmamento (ES)" },
  { "Data": "23/10", "Comemorar": "Dia Estadual da Leitura (PE)" },
  { "Data": "23/10", "Comemorar": "Dia do Aposentado do Banco Central" },
  { "Data": "23/10", "Comemorar": "Dia da Comunidade Húngara (SP)" },
  { "Data": "23/10", "Comemorar": "Dia da Aerofilatelia" },
  { "Data": "24/10", "Comemorar": "Dia Mundial do Desenvolvimento" },
  { "Data": "24/10", "Comemorar": "Aniversário da Cidade de Goiânia" },
  { "Data": "24/10", "Comemorar": "Aniversário da Cidade de Manaus" },
  { "Data": "24/10", "Comemorar": "Dia das Nações Unidas, ou Dia da ONU" },
  { "Data": "24/10", "Comemorar": "Dia Mundial de Combate à Poliomielite" },
  { "Data": "24/10", "Comemorar": "Dia Internacional das Missões" },
  { "Data": "25/10", "Comemorar": "Dia da Democracia" },
  { "Data": "25/10", "Comemorar": "Dia do Dentista" },
  { "Data": "25/10", "Comemorar": "Dia do Cirurgião-dentista" },
  { "Data": "25/10", "Comemorar": "Dia Nacional de Saúde Bucal" },
  { "Data": "25/10", "Comemorar": "Dia da Construção Civil" },
  { "Data": "25/10", "Comemorar": "Dia do Sapateiro" },
  { "Data": "25/10", "Comemorar": "Dia Mundial do Macarrão" },
  { "Data": "25/10", "Comemorar": "Dia Mundial da Temperança" },
  { "Data": "25/10", "Comemorar": "Dia de São Frei Galvão" },
  { "Data": "26/10", "Comemorar": "Dia do Trabalhador da Construção Civil" },
  { "Data": "26/10", "Comemorar": "Dia Oficial do Músico" },
  { "Data": "26/10", "Comemorar": "Dia de Santo Evaristo" },
  { "Data": "27/10", "Comemorar": "Dia Mundial de Oração pela Paz" },
  { "Data": "27/10", "Comemorar": "World Occupational Therapy Day" },
  {
    "Data": "27/10",
    "Comemorar": "Dia Nacional de Mobilização Pró-saúde da População Negra"
  },
  { "Data": "27/10", "Comemorar": "Dia Mundial do Patrimônio Audiovisual" },
  { "Data": "27/10", "Comemorar": "Dia Estadual do Artista Plástico (MT)" },
  {
    "Data": "27/10",
    "Comemorar": "Dia Estadual de Prevenção de Câncer de Colo Uterino (PE)"
  },
  {
    "Data": "27/10",
    "Comemorar": "Dia do Passeio Ciclístico Ecológico (SP) em 2024"
  },
  { "Data": "28/10", "Comemorar": "Dia do Funcionário Público" },
  { "Data": "28/10", "Comemorar": "Dia da Engenharia da Aeronáutica" },
  { "Data": "28/10", "Comemorar": "Dia Mundial do Judô" },
  { "Data": "28/10", "Comemorar": "Dia de São Judas Tadeu" },
  { "Data": "28/10", "Comemorar": "Dia Internacional da Animação" },
  {
    "Data": "28/10",
    "Comemorar": "Dia Internacional da Biblioteca Escolar em 2024"
  },
  { "Data": "29/10", "Comemorar": "Dia Nacional do Livro" },
  { "Data": "29/10", "Comemorar": "Dia das Flores" },
  { "Data": "29/10", "Comemorar": "Dia Nacional de Combate à Psoríase" },
  { "Data": "29/10", "Comemorar": "Dia Mundial do Acidente Vascular Cerebral" },
  { "Data": "30/10", "Comemorar": "Dia do Protestante" },
  { "Data": "30/10", "Comemorar": "Dia do Comerciário" },
  { "Data": "30/10", "Comemorar": "Dia da Decoração" },
  { "Data": "30/10", "Comemorar": "Dia Nacional de Luta Contra o Reumatismo" },
  { "Data": "30/10", "Comemorar": "Dia Nacional do Ginecologista e Obstetra" },
  { "Data": "30/10", "Comemorar": "Dia do Atentendente dos Correios" },
  { "Data": "30/10", "Comemorar": "Dia do Balconista" },
  {
    "Data": "30/10",
    "Comemorar": "Dia do Material Bélico do Exército Brasileiro"
  },
  { "Data": "31/10", "Comemorar": "Dia da Dona de Casa" },
  { "Data": "31/10", "Comemorar": "Halloween - Dia das Bruxas" },
  { "Data": "31/10", "Comemorar": "Dia Mundial da Economia " },
  { "Data": "31/10", "Comemorar": "Dia Mundial da Poupança" },
  { "Data": "31/10", "Comemorar": "Dia do Repórter Policial" },
  { "Data": "31/10", "Comemorar": "Dia D – Dia Drummond" },
  { "Data": "31/10", "Comemorar": "Dia Mundial do Comissário de Voo" },
  { "Data": "31/10", "Comemorar": "Dia Nacional da Proclamação do Evangelho" },
  { "Data": "31/10", "Comemorar": "Dia da Reforma Luterana" },
  { "Data": "01/11", "Comemorar": "Dia de Todos os Santos" },
  { "Data": "01/11", "Comemorar": "Dia de São Benigno" },
  { "Data": "01/11", "Comemorar": "Dia Mundial Vegano" },
  { "Data": "01/11", "Comemorar": "Dia do Frevo de Bloco (PE)" },
  { "Data": "01/11", "Comemorar": "Dia do Sepultador (SP)" },
  { "Data": "01/11", "Comemorar": "Dia do Colecionador Capixaba" },
  { "Data": "01/11", "Comemorar": "Dia do Romeiro (CE)" },
  { "Data": "01/11", "Comemorar": "Dia do Sushi (Japão)" },
  { "Data": "01/11", "Comemorar": "National Cook For Your Pets Day (EUA)" },
  { "Data": "02/11", "Comemorar": "Dia de Finados" },
  {
    "Data": "02/11",
    "Comemorar": "Dia Mundial pelo Fim da Impunidade dos Crimes contra Jornalistas"
  },
  { "Data": "03/11", "Comemorar": "Dia da Censura" },
  { "Data": "03/11", "Comemorar": "Dia do Guarda-florestal" },
  { "Data": "03/11", "Comemorar": "Dia do Profissional da Beleza (RJ)" },
  { "Data": "03/11", "Comemorar": "Dia da Solidariedade (SP)" },
  { "Data": "03/11", "Comemorar": "Dia da Cidadania (RS)" },
  { "Data": "03/11", "Comemorar": "International Day for Biosphere Reserves" },
  { "Data": "04/11", "Comemorar": "Dia da União dos Escoteiros do Brasil" },
  { "Data": "04/11", "Comemorar": "Dia do Oficial da Reserva R/2" },
  { "Data": "04/11", "Comemorar": "Dia de São Carlos Borromeu" },
  { "Data": "04/11", "Comemorar": "Dia Batista de Oração Mundial em 2024" },
  { "Data": "05/11", "Comemorar": "Dia da Ciência" },
  { "Data": "05/11", "Comemorar": "Dia Nacional da Cultura" },
  { "Data": "05/11", "Comemorar": "Dia do Design" },
  { "Data": "05/11", "Comemorar": "Dia do Técnico Agrícola" },
  { "Data": "05/11", "Comemorar": "Dia Mundial do Inventor" },
  { "Data": "05/11", "Comemorar": "Dia do Protético" },
  { "Data": "05/11", "Comemorar": "Dia Nacional do Radioamador" },
  { "Data": "05/11", "Comemorar": "Dia do Técnico em Eletrônica" },
  { "Data": "05/11", "Comemorar": "Dia do Corpo de Saúde da Marinha" },
  { "Data": "05/11", "Comemorar": "Dia do Escrivão de Polícia" },
  {
    "Data": "05/11",
    "Comemorar": "Dia Mundial da Conscientização sobre Tsunâmis"
  },
  { "Data": "06/11", "Comemorar": "Dia de São Teófilo Venard" },
  { "Data": "06/11", "Comemorar": "Dia Nacional do Amigo da Marinha" },
  { "Data": "07/11", "Comemorar": "Dia da Ação Católica" },
  { "Data": "07/11", "Comemorar": "Dia Estadual do Radialista (MS)" },
  {
    "Data": "07/11",
    "Comemorar": "Dia Nacional de Luta Pela Regularização Fundiária"
  },
  { "Data": "08/11", "Comemorar": "Dia Mundial do Urbanismo" },
  { "Data": "08/11", "Comemorar": "Dia do Radiologista" },
  { "Data": "09/11", "Comemorar": "Dia Nacional do Hoteleiro" },
  { "Data": "09/11", "Comemorar": "Dia Estadual da Mamografia (MT)" },
  {
    "Data": "09/11",
    "Comemorar": "Dia Internacional contra o Fascismo e o Anti-Semitismo"
  },
  { "Data": "09/11", "Comemorar": "Carl Sagan Day" },
  { "Data": "10/11", "Comemorar": "Dia Nacional da Nota Fiscal" },
  { "Data": "10/11", "Comemorar": "Dia Nacional do Doente Auditivo" },
  { "Data": "10/11", "Comemorar": "Dia da Esquadra" },
  { "Data": "11/11", "Comemorar": "Dia Nacional do Supermercado" },
  { "Data": "11/11", "Comemorar": "Dia do Procurador do Estado de Goiás" },
  { "Data": "11/11", "Comemorar": "Dia dos Veteranos (EUA)" },
  { "Data": "11/11", "Comemorar": "Dia do Armistício" },
  { "Data": "11/11", "Comemorar": "Dia das Cataratas do Iguaçu" },
  { "Data": "12/11", "Comemorar": "Dia do Diretor de Escola" },
  { "Data": "12/11", "Comemorar": "Dia das Federações Esportivas (SP)" },
  { "Data": "12/11", "Comemorar": "Dia do Caju (CE)" },
  {
    "Data": "12/11",
    "Comemorar": "Dia Estadual do Profissional de Psicopedagogia (GO)"
  },
  { "Data": "12/11", "Comemorar": "Dia do Laçador (MS)" },
  { "Data": "12/11", "Comemorar": "Dia da Liberdade (MG)" },
  { "Data": "12/11", "Comemorar": "Dia Mundial do Hip Hop" },
  { "Data": "13/11", "Comemorar": "Dia de Santo Estanislau Kostka" },
  { "Data": "13/11", "Comemorar": "Dia Mundial da Gentileza" },
  { "Data": "14/11", "Comemorar": "Dia Nacional da Alfabetização" },
  { "Data": "14/11", "Comemorar": "Dia Mundial da Diabetes" },
  { "Data": "14/11", "Comemorar": "Dia do Bandeirante" },
  { "Data": "14/11", "Comemorar": "Dia Internacional da Qualidade em 2024" },
  { "Data": "15/11", "Comemorar": "Dia da República Federativa do Brasil" },
  { "Data": "15/11", "Comemorar": "Dia do Joalheiro" },
  { "Data": "15/11", "Comemorar": "Dia Nacional da Umbanda" },
  { "Data": "15/11", "Comemorar": "America Recycles Day" },
  { "Data": "16/11", "Comemorar": "Dia Internacional da Tolerância" },
  { "Data": "16/11", "Comemorar": "Dia Internacional do Patrimônio Mundial" },
  { "Data": "16/11", "Comemorar": "Dia Nacional de Atenção à Dislexia" },
  { "Data": "16/11", "Comemorar": "Dia do Policial Federal" },
  { "Data": "16/11", "Comemorar": "Dia da Tradição Oral" },
  { "Data": "16/11", "Comemorar": "Dia Nacional dos Ostomizados" },
  { "Data": "16/11", "Comemorar": "Dia Nacional da Amazônia Azul" },
  { "Data": "17/11", "Comemorar": "Dia da Criatividade" },
  { "Data": "17/11", "Comemorar": "Dia Internacional do Estudante" },
  { "Data": "17/11", "Comemorar": "Dia Nacional de Combate à Tuberculose" },
  { "Data": "17/11", "Comemorar": "Dia do Flamengo (RJ)" },
  {
    "Data": "17/11",
    "Comemorar": "Dia Mundial em Memória das Vítimas de Trânsito em 2024"
  },
  { "Data": "18/11", "Comemorar": "Dia de Santo Edmundo" },
  { "Data": "18/11", "Comemorar": "Dia do Barroco Mineiro" },
  { "Data": "18/11", "Comemorar": "Dia do Líder Comunitário (RJ)" },
  { "Data": "18/11", "Comemorar": "Dia do Conselheiro Tutelar" },
  { "Data": "18/11", "Comemorar": "Dia Nacional de Combate ao Racismo" },
  { "Data": "19/11", "Comemorar": "Dia da Bandeira Nacional" },
  { "Data": "19/11", "Comemorar": "Dia Internacional do Xadrez" },
  { "Data": "19/11", "Comemorar": "Dia Mundial do Empreendedorismo Feminino" },
  { "Data": "20/11", "Comemorar": "Dia do Auditor Interno" },
  { "Data": "20/11", "Comemorar": "Dia do Biomédico" },
  { "Data": "20/11", "Comemorar": "Dia do Músico Evangélico" },
  { "Data": "20/11", "Comemorar": "Dia do Profissional Liberal Universitário" },
  { "Data": "20/11", "Comemorar": "Dia Nacional da Consciência Negra" },
  {
    "Data": "20/11",
    "Comemorar": "Dia do Empoderamento do Cabelo Crespo (Salvador - BA)"
  },
  { "Data": "20/11", "Comemorar": "Dia Internacional da Infância" },
  {
    "Data": "20/11",
    "Comemorar": "Dia Mundial de Combate à Doença Pulmonar Obstrutiva em 2024"
  },
  { "Data": "21/11", "Comemorar": "Dia do Homeopata" },
  { "Data": "21/11", "Comemorar": "Dia Mundial da Televisão" },
  { "Data": "21/11", "Comemorar": "Dia do Parlamentar Fluminense" },
  { "Data": "21/11", "Comemorar": "Dia das Saudações" },
  {
    "Data": "22/11",
    "Comemorar": "Dia Universal da Música (homenagem à Santa Cecília)"
  },
  { "Data": "22/11", "Comemorar": "Dia de Santa Cecília" },
  { "Data": "22/11", "Comemorar": "Dia da Comunidade Libanesa no Brasil" },
  { "Data": "23/11", "Comemorar": "Dia de São Clemente" },
  {
    "Data": "23/11",
    "Comemorar": "Dia Nacional de Combate ao Câncer Infantil"
  },
  { "Data": "23/11", "Comemorar": "Dia da Capoeira (RJ)" },
  { "Data": "23/11", "Comemorar": "Dia Mundial da Aquarela" },
  { "Data": "24/11", "Comemorar": "Dia Nacional dos Rios" },
  { "Data": "24/11", "Comemorar": "Dia do Rio Beberibe (PE)" },
  {
    "Data": "24/11",
    "Comemorar": "Dia do Quadro Auxiliar de Oficiais do Exército"
  },
  { "Data": "24/11", "Comemorar": "Dia do Vinho Argentino" },
  { "Data": "24/11", "Comemorar": "Dia do Ministro de Música Batista em 2024" },
  { "Data": "25/11", "Comemorar": "Dia Universal do Doador de Sangue" },
  { "Data": "25/11", "Comemorar": "Dia da Baiana do Acarajé - BA" },
  {
    "Data": "25/11",
    "Comemorar": "Dia Internacional para a Eliminação da Violência Contra as Mulheres"
  },
  { "Data": "25/11", "Comemorar": "Dia Nacional do Doador de Sangue" },
  { "Data": "26/11", "Comemorar": "Dia do Ministério Público" },
  { "Data": "26/11", "Comemorar": "Dia do Corpo Auxiliar da Marinha" },
  { "Data": "26/11", "Comemorar": "Dia do Mototaxista (PB)" },
  { "Data": "26/11", "Comemorar": "Dia do Balconista de Autopeças (SP)" },
  { "Data": "26/11", "Comemorar": "Dia da Melancia" },
  { "Data": "27/11", "Comemorar": "Dia do Técnico de Segurança do Trabalho" },
  { "Data": "27/11", "Comemorar": "Dia da Afirmação Democrática" },
  { "Data": "27/11", "Comemorar": "Dia de Santa Catarina Labouré" },
  { "Data": "27/11", "Comemorar": "Dia Nacional de Combate ao Câncer" },
  {
    "Data": "27/11",
    "Comemorar": "Dia da medalha milagrosa de Nossa Senhora das Graças"
  },
  { "Data": "27/11", "Comemorar": "Dia de São João Crisóstomo" },
  { "Data": "28/11", "Comemorar": "Dia do Soldado Desconhecido" },
  { "Data": "28/11", "Comemorar": "Dia Internacional do Ministério Público" },
  { "Data": "28/11", "Comemorar": "Dia de São Tiago de Marca" },
  { "Data": "28/11", "Comemorar": "Dia Nacional de Ação de Graças em 2024" },
  { "Data": "29/11", "Comemorar": "Dia de São Saturnino" },
  {
    "Data": "29/11",
    "Comemorar": "Dia Internacional de Solidariedade com o Povo Palestino"
  },
  { "Data": "29/11", "Comemorar": "Dia da Criança Prematura (RJ)" },
  { "Data": "30/11", "Comemorar": "Dia do Síndico" },
  { "Data": "30/11", "Comemorar": "Dia do Estatuto da Terra" },
  { "Data": "30/11", "Comemorar": "Dia da Reforma Agrária" },
  { "Data": "30/11", "Comemorar": "Dia do Teólogo" },
  { "Data": "30/11", "Comemorar": "Dia de Santo André" },
  { "Data": "01/12", "Comemorar": "Dia Internacional de Combate à AIDS" },
  {
    "Data": "01/12",
    "Comemorar": "Dia Estadual de Repressão ao Tráfico de Animais Silvestres (RJ)"
  },
  { "Data": "01/12", "Comemorar": "Dia do Numismata" },
  { "Data": "01/12", "Comemorar": "Dia de Santo Elói" },
  { "Data": "01/12", "Comemorar": "Dia de Santo Elígio" },
  { "Data": "02/12", "Comemorar": "Dia Nacional de Astronomia" },
  { "Data": "02/12", "Comemorar": "Dia Panamericano da Saúde" },
  { "Data": "02/12", "Comemorar": "Dia do Advogado Criminalista" },
  { "Data": "02/12", "Comemorar": "Dia Nacional do Samba" },
  { "Data": "02/12", "Comemorar": "Dia Nacional das Relações Públicas" },
  { "Data": "02/12", "Comemorar": "Dia do Serviço de Saúde da Aeronáutica" },
  {
    "Data": "02/12",
    "Comemorar": "Dia Internacional para a Abolição da Escravidão"
  },
  { "Data": "03/12", "Comemorar": "Dia de São Francisco Xavier" },
  {
    "Data": "03/12",
    "Comemorar": "Dia Internacional de Luta dos Portadores de Deficiência"
  },
  { "Data": "03/12", "Comemorar": "Dia do Selecionador de Pessoal" },
  { "Data": "03/12", "Comemorar": "Dia Nacional de Combate à Pirataria" },
  { "Data": "03/12", "Comemorar": "Dia do Delegado de Polícia (DF)" },
  { "Data": "03/12", "Comemorar": "Dia da Medicina Latinoamericana" },
  { "Data": "04/12", "Comemorar": "Dia do Orientador Escolar" },
  { "Data": "04/12", "Comemorar": "Dia do Podólogo" },
  { "Data": "04/12", "Comemorar": "Dia Mundial da Propaganda" },
  { "Data": "04/12", "Comemorar": "Dia do Orientador Educacional" },
  { "Data": "04/12", "Comemorar": "Dia do Perito Criminal Oficial" },
  { "Data": "04/12", "Comemorar": "Dia do Trabalhador em Minas de Carvão" },
  { "Data": "04/12", "Comemorar": "Dia de Santa Bárbara" },
  { "Data": "04/12", "Comemorar": "Dia de São João Damasceno" },
  { "Data": "04/12", "Comemorar": "Dia Internacional da Câmara Júnior" },
  { "Data": "05/12", "Comemorar": "Dia da Cruz Vermelha Brasileira" },
  {
    "Data": "05/12",
    "Comemorar": "Dia do Médico de Saúde da Família e Comunidade"
  },
  {
    "Data": "05/12",
    "Comemorar": "Dia Internacional dos Voluntários para o Desenvolvimento Econômico e Social"
  },
  { "Data": "05/12", "Comemorar": "Dia Internacional do Solo" },
  { "Data": "06/12", "Comemorar": "Dia de São Nicolau" },
  { "Data": "06/12", "Comemorar": "Dia do Madeireiro" },
  { "Data": "06/12", "Comemorar": "Dia da Extensão Rural" },
  { "Data": "07/12", "Comemorar": "Dia Internacional da Aviação Civil" },
  { "Data": "07/12", "Comemorar": "Dia Nacional da Assistência Social" },
  { "Data": "07/12", "Comemorar": "Dia Nacional da Silvicultura" },
  { "Data": "07/12", "Comemorar": "Dia Estadual do Oficial de Justiça (RS)" },
  { "Data": "07/12", "Comemorar": "National Cotton Candy Day" },
  { "Data": "08/12", "Comemorar": "Dia Internacional da Justiça" },
  { "Data": "08/12", "Comemorar": "Dia do Cronista Esportivo" },
  { "Data": "08/12", "Comemorar": "Dia Nacional da Família" },
  { "Data": "08/12", "Comemorar": "Dia da Mulata" },
  { "Data": "08/12", "Comemorar": "Dia da Imaculada Conceição" },
  { "Data": "08/12", "Comemorar": "Dia Mundial do Canto Coral em 2024" },
  { "Data": "08/12", "Comemorar": "Dia da Bíblia em 2024" },
  { "Data": "09/12", "Comemorar": "Dia do Fonoaudiólogo" },
  { "Data": "09/12", "Comemorar": "Dia do Alcoólico Recuperado" },
  { "Data": "09/12", "Comemorar": "Dia Internacional Contra a Corrupção" },
  { "Data": "09/12", "Comemorar": "Dia do Profissional de Culinária" },
  { "Data": "09/12", "Comemorar": "Dia de Santa Leocádia" },
  { "Data": "10/12", "Comemorar": "Dia do Palhaço" },
  { "Data": "10/12", "Comemorar": "Dia Estadual do Previdenciário - SP" },
  { "Data": "10/12", "Comemorar": "Dia de São Melquíades" },
  { "Data": "10/12", "Comemorar": "Dia Internacional dos Direitos Humanos" },
  { "Data": "11/12", "Comemorar": "Dia do Agrimensor" },
  { "Data": "11/12", "Comemorar": "Dia da Infantaria da Aeronáutica" },
  { "Data": "11/12", "Comemorar": "Dia do Engenheiro" },
  { "Data": "11/12", "Comemorar": "Dia do Evangelho" },
  { "Data": "11/12", "Comemorar": "Dia do Tango" },
  { "Data": "11/12", "Comemorar": "Dia Internacional das Montanhas" },
  { "Data": "11/12", "Comemorar": "Dia de São Dâmaso" },
  { "Data": "12/12", "Comemorar": "Dia de Nossa Senhora de Guadalupe" },
  { "Data": "12/12", "Comemorar": "Aniversário da Cidade de Belo Horizonte" },
  { "Data": "12/12", "Comemorar": "Dia do Plano Nacional de Educação" },
  { "Data": "13/12", "Comemorar": "Dia do Avaliador" },
  { "Data": "13/12", "Comemorar": "Dia do Cego" },
  { "Data": "13/12", "Comemorar": "Dia do Marinheiro" },
  { "Data": "13/12", "Comemorar": "Dia do Lapidador" },
  { "Data": "13/12", "Comemorar": "Dia Estadual do Sanfoneiro - PE" },
  { "Data": "13/12", "Comemorar": "Dia Nacional do Forró" },
  { "Data": "13/12", "Comemorar": "Dia do Pedreiro" },
  { "Data": "13/12", "Comemorar": "Dia de Santa Luzia" },
  { "Data": "14/12", "Comemorar": "Dia Nacional da Ópera" },
  { "Data": "14/12", "Comemorar": "Dia do Engenheiro de Pesca" },
  { "Data": "14/12", "Comemorar": "Dia de São João da Cruz" },
  { "Data": "15/12", "Comemorar": "Dia do Jardineiro" },
  { "Data": "15/12", "Comemorar": "Dia do Jornaleiro" },
  { "Data": "15/12", "Comemorar": "Dia do Esperanto" },
  { "Data": "15/12", "Comemorar": "Dia Nacional do Arquiteto e Urbanista" },
  { "Data": "15/12", "Comemorar": "Dia da Mulher Profissional de Direito" },
  { "Data": "16/12", "Comemorar": "Dia do Teatro Amador" },
  { "Data": "16/12", "Comemorar": "Dia do Reservista" },
  { "Data": "16/12", "Comemorar": "Dia de Santa Adelaide" },
  { "Data": "16/12", "Comemorar": "Dia de São José Moscati" },
  { "Data": "17/12", "Comemorar": "Dia de São Lázaro" },
  { "Data": "17/12", "Comemorar": "Dia do Presbiteriano" },
  { "Data": "17/12", "Comemorar": "Dia de Santa Olímpia" },
  { "Data": "18/12", "Comemorar": "Dia Internacional do Imigrante" },
  { "Data": "18/12", "Comemorar": "Dia do Museólogo" },
  { "Data": "18/12", "Comemorar": "Dia da Bailarina (SP)" },
  { "Data": "19/12", "Comemorar": "Dia do Aniversário do Estado do Paraná" },
  { "Data": "19/12", "Comemorar": "Dia Estadual da Poesia (MT)" },
  { "Data": "19/12", "Comemorar": "Dia de Santo Urbano V" },
  { "Data": "20/12", "Comemorar": "Dia da Bondade" },
  { "Data": "20/12", "Comemorar": "Dia do Mecânico" },
  { "Data": "21/12", "Comemorar": "Dia do Artista Profissional" },
  { "Data": "21/12", "Comemorar": "Dia de São Pedro Canísio" },
  { "Data": "21/12", "Comemorar": "Início do verão no hemisfério sul" },
  { "Data": "21/12", "Comemorar": "Início do inverno no hemisfério norte" },
  { "Data": "21/12", "Comemorar": "Dia do Gestor Imobiliário (RJ)" },
  { "Data": "22/12", "Comemorar": "Dia da Consciência Ecológica" },
  { "Data": "22/12", "Comemorar": "Dia de Santa Francisca Xavier Cabrini" },
  { "Data": "23/12", "Comemorar": "Dia do Vizinho" },
  { "Data": "23/12", "Comemorar": "Dia do Atleta Amador" },
  { "Data": "23/12", "Comemorar": "Dia da Carteira de Habilitação" },
  { "Data": "23/12", "Comemorar": "Dia de São João Câncio" },
  { "Data": "24/12", "Comemorar": "Dia Nacional do Órfão" },
  { "Data": "24/12", "Comemorar": "Dia Universal do Perdão" },
  { "Data": "24/12", "Comemorar": "Dia de São Charbel Makhlouf" },
  { "Data": "25/12", "Comemorar": "Dia de Natal" },
  { "Data": "25/12", "Comemorar": "Dia Estadual da Parteira Tradicional (PA)" },
  { "Data": "26/12", "Comemorar": "Dia da Lembrança" },
  { "Data": "26/12", "Comemorar": "Dia de Santo Estevão" },
  { "Data": "26/12", "Comemorar": "Dia do Pedreiro (SP)" },
  { "Data": "27/12", "Comemorar": "Dia de São João Apóstolo" },
  {
    "Data": "27/12",
    "Comemorar": "Dia Internacional de Preparação para Epidemias"
  },
  { "Data": "28/12", "Comemorar": "Dia da Marinha Mercante" },
  { "Data": "28/12", "Comemorar": "Dia do Salva-Vidas" },
  { "Data": "28/12", "Comemorar": "Dia Nacional do Cooperativismo de Crédito" },
  { "Data": "28/12", "Comemorar": "Dia dos Santos Inocentes" },
  { "Data": "29/12", "Comemorar": "Dia de Santo Tomás Becket" },
  { "Data": "30/12", "Comemorar": "Dia de São Sabino" },
  { "Data": "31/12", "Comemorar": "Dia da Esperança" },
  { "Data": "31/12", "Comemorar": "Dia de São Silvestre" }
]
